[
    {
        "url": "https://finance.yahoo.com/news/nvidias-auto-business-surges-69-from-self-driving-tech-170844143.html",
        "title": "Nvidia's auto business surges 69% from self-driving tech"
    },
    {
        "url": "https://finance.yahoo.com/news/nvidia-stock-slides-3-amid-broader-chip-sell-off-after-dell-results-alibaba-competition-170756106.html",
        "title": "Nvidia stock slides 3% amid broader chip sell-off after Dell results, Alibaba competition"
    },
    {
        "url": "https://finance.yahoo.com/news/why-wall-street-developed-unhealthy-150005740.html",
        "title": "Why Wall Street has developed an unhealthy obsession with Nvidia"
    },
    {
        "url": "https://finance.yahoo.com/news/james-altucher-spotlights-elon-musk-150000942.html",
        "title": "James Altucher Spotlights Elon Musk\u2019s Role in America\u2019s AI Revolution"
    },
    {
        "url": "https://finance.yahoo.com/news/truist-upgrades-advanced-micro-devices-141531391.html",
        "title": "Truist Upgrades Advanced Micro Devices (AMD) to Buy, Lifts Price Target to $213"
    },
    {
        "url": "https://finance.yahoo.com/news/youd-invested-10-000-nvidia-141500178.html",
        "title": "If You'd Invested $10,000 in Nvidia Stock 10 Years Ago, Here's How Much You'd Have Today"
    },
    {
        "url": "https://finance.yahoo.com/news/does-surgeon-led-hemopatch-launch-101541773.html",
        "title": "Does Surgeon-Led Hemopatch Launch Mark a New Innovation Edge for Baxter (BAX)?"
    },
    {
        "url": "https://finance.yahoo.com/news/strong-overseas-demand-guidance-jinkosolar-101103455.html",
        "title": "How Strong Overseas Demand and New Guidance at JinkoSolar (JKS) Has Changed Its Investment Story"
    },
    {
        "url": "https://finance.yahoo.com/news/nvidia-facing-biggest-challenge-yet-090000593.html",
        "title": "Nvidia is facing its biggest challenge yet: The law of large numbers"
    },
    {
        "url": "https://finance.yahoo.com/news/growth-stocks-heres-1-every-084000595.html",
        "title": "New to Growth Stocks? Here's 1 Every Investor Should Have on Their Radar."
    },
    {
        "url": "https://finance.yahoo.com/news/investing-com-stocks-week-083002820.html",
        "title": "Investing.com\u2019s stocks of the week"
    },
    {
        "url": "https://finance.yahoo.com/news/2-artificial-intelligence-ai-stocks-082900843.html",
        "title": "2 Artificial Intelligence (AI) Stocks to Buy Before They Soar Under President Trump"
    },
    {
        "url": "https://finance.yahoo.com/news/prediction-monster-artificial-intelligence-ai-082000130.html",
        "title": "Prediction: This Monster Artificial Intelligence (AI) Chip Stock Will Soar in September (Hint: It's Not Nvidia)"
    },
    {
        "url": "https://finance.yahoo.com/news/meta-platforms-apple-just-gave-081000166.html",
        "title": "Meta Platforms and Apple Just Gave This Fellow \"Magnificent Seven\" Stock Great News"
    },
    {
        "url": "https://finance.yahoo.com/news/buy-nvidia-blowout-earnings-report-074500729.html",
        "title": "Should You Buy Nvidia After Its Blowout Earnings Report? Here's What History Says."
    },
    {
        "url": "https://finance.yahoo.com/news/trump-fed-meddling-pushes-investors-040037529.html",
        "title": "Trump\u2019s Fed meddling pushes investors closer to their red line"
    },
    {
        "url": "https://finance.yahoo.com/news/lambda-taps-super-micro-computer-034249522.html",
        "title": "Lambda Taps Super Micro Computer Inc. (SMCI)\u2019s GPUs Optimized for Servers"
    }
]