[
    {
        "url": "https://finance.yahoo.com/news/ulty-weekly-payouts-look-generous-154521342.html",
        "title": "ULTY\u2019s Weekly Payouts Look Generous Until You See Where the Money Is Coming From"
    },
    {
        "url": "https://finance.yahoo.com/news/tesla-terafab-macrohard-push-ai-152216788.html",
        "title": "Tesla Terafab And Macrohard Push AI Ambitions And Test Rich Valuation"
    },
    {
        "url": "https://finance.yahoo.com/news/warren-buffett-invested-tesla-145216067.html",
        "title": "Is Warren Buffett Invested in Tesla?"
    },
    {
        "url": "https://finance.yahoo.com/news/week-ahead-investors-face-busy-143500615.html",
        "title": "Week ahead: Investors face busy week as Fed and tech take center stage"
    },
    {
        "url": "https://finance.yahoo.com/news/tesla-pivot-robotics-ai-likely-122405838.html",
        "title": "How is Tesla\u2019s pivot to robotics and AI likely to affect it going forward?"
    },
    {
        "url": "https://finance.yahoo.com/news/assessing-tesla-tsla-valuation-terafab-110850968.html",
        "title": "Assessing Tesla (TSLA) Valuation After Terafab AI Chip Launch And Surging China Deliveries"
    },
    {
        "url": "https://finance.yahoo.com/news/social-buzz-wallstreetbets-stocks-advance-105119443.html",
        "title": "Social Buzz: Wallstreetbets Stocks Advance Premarket Monday; Nebius Group, Micron Technology to Open Higher"
    },
    {
        "url": "https://finance.yahoo.com/news/tesla-investors-extremely-nervous-104500796.html",
        "title": "This Should Make Tesla Investors Extremely Nervous"
    },
    {
        "url": "https://finance.yahoo.com/news/tesla-syrah-extend-graphite-supply-100241714.html",
        "title": "Tesla and Syrah Extend Graphite Supply Dispute Deadline"
    },
    {
        "url": "https://finance.yahoo.com/news/rivian-automotive-inc-rivn-good-001145864.html",
        "title": "Is Rivian Automotive, Inc. (RIVN) A Good Stock To Buy Now?"
    },
    {
        "url": "https://finance.yahoo.com/news/most-overlooked-artificial-intelligence-ai-224500465.html",
        "title": "The Most Overlooked Artificial Intelligence (AI) Stocks in the \"Magnificent Seven\" for 2026"
    },
    {
        "url": "https://finance.yahoo.com/news/elon-musk-unmasks-joint-project-193625414.html",
        "title": "Elon Musk Unmasks Joint Project Between Tesla (TSLA) and xAI, Reuters Reports"
    },
    {
        "url": "https://finance.yahoo.com/news/top-growth-stock-buy-2026-180500904.html",
        "title": "My Top Growth Stock to Buy for 2026 (and It's Not Even Close)"
    },
    {
        "url": "https://finance.yahoo.com/news/elon-musk-issues-apology-not-164700162.html",
        "title": "Elon Musk issues apology for not building xAI right"
    },
    {
        "url": "https://finance.yahoo.com/news/elon-musk-says-100-way-153125383.html",
        "title": "Elon Musk Says 100% 'This Is The Way' Endorsing Warren Buffett's Famous 5-Minute Plan to Fix the Deficit \u2013 And It Has Nothing To Do With Your Taxes"
    }
]