[
    {
        "url": "https://finance.yahoo.com/news/a-broadening-playbook-wall-street-sees-stock-market-gains-beyond-tech-160556466.html",
        "title": "'A broadening playbook': Wall Street sees stock market gains beyond tech"
    },
    {
        "url": "https://finance.yahoo.com/news/tesla-benefit-canada-lifts-tariffs-153818841.html",
        "title": "Tesla to Benefit as Canada Lifts Tariffs on Chinese Made EVs"
    },
    {
        "url": "https://finance.yahoo.com/news/tesla-cathie-wood-says-robotaxis-153255341.html",
        "title": "Tesla: Cathie Wood Says Robotaxis Are the Real Growth Engine"
    },
    {
        "url": "https://finance.yahoo.com/news/wall-street-pushes-volatility-trades-134225495.html",
        "title": "Wall Street Pushes Volatility Trades as AI Rally Meets Policy Risk"
    },
    {
        "url": "https://finance.yahoo.com/news/clickhouse-secures-400m-series-d-123835366.html",
        "title": "ClickHouse secures $400m in Series D led by Dragoneer"
    },
    {
        "url": "https://finance.yahoo.com/news/tesla-nasdaq-tsla-bull-bear-153808849.html",
        "title": "Tesla (NASDAQ: TSLA) Bull, Base and Bear Price Prediction and Forecast"
    },
    {
        "url": "https://finance.yahoo.com/news/autonomous-driving-market-sees-robust-114300151.html",
        "title": "Autonomous Driving Market Sees Robust Growth with CAGR of 17.63% Expected By 2033 | Astute Analytica"
    },
    {
        "url": "https://finance.yahoo.com/news/sec-approves-expanded-option-expirations-113650138.html",
        "title": "SEC Approves Expanded Option Expirations for Magnificent Seven Stocks"
    },
    {
        "url": "https://finance.yahoo.com/news/tesla-accelerates-silicon-roadmap-ai5-113400470.html",
        "title": "Tesla Accelerates Silicon Roadmap with AI5 and AI6 Cycles"
    },
    {
        "url": "https://finance.yahoo.com/news/tsla-vs-byddy-whats-better-085400157.html",
        "title": "TSLA vs. BYDDY: What's the Better Long-Term Play?"
    },
    {
        "url": "https://finance.yahoo.com/news/tesla-poised-early-winner-canada-063806836.html",
        "title": "Tesla poised to be early winner as Canada opens door to Chinese-made EVs"
    },
    {
        "url": "https://finance.yahoo.com/news/palantir-billionaire-peter-thiel-sells-065800486.html",
        "title": "Palantir Billionaire Peter Thiel Sells Nvidia and Tesla Shares, Then Buys an AI Stock That's Up Nearly 460,000% Since Its IPO"
    },
    {
        "url": "https://finance.yahoo.com/news/syrah-extends-tesla-offtake-cure-013346603.html",
        "title": "Syrah Extends Tesla Offtake Cure Deadline as Vidalia Qualification Continues"
    },
    {
        "url": "https://finance.yahoo.com/news/assessing-tesla-tsla-valuation-recent-010902315.html",
        "title": "Assessing Tesla (TSLA) Valuation After Recent Share Price Pullback And AI Growth Ambitions"
    },
    {
        "url": "https://finance.yahoo.com/news/australias-syrah-resources-buys-more-235709376.html",
        "title": "Australia's Syrah Resources buys more time for Tesla graphite supply deal"
    },
    {
        "url": "https://finance.yahoo.com/news/tesla-fires-america-first-major-220000149.html",
        "title": "Tesla Fires Up America\u2019s First Major Lithium Refinery"
    },
    {
        "url": "https://finance.yahoo.com/news/tesla-struggling-global-ev-market-153109260.html",
        "title": "Tesla Is Struggling \u2014 The Global EV Market Isn't"
    }
]