[
    {
        "url": "https://finance.yahoo.com/news/jim-cramer-mentions-amazon-com-160706831.html",
        "title": "Jim Cramer Mentions Amazon.com, Inc. (AMZN) & AI",
        "detail": "Jim Cramer Mentions Amazon.com, Inc. (AMZN) & AI\nRamish Cheema\nTue, Sep 23, 2025, 9:07 AM 2 min read\nIn this article:\nAMZN\nNVDA\n\nWe recently published 12 Hot, Cold & Stable Stocks Jim Cramer Recently Discussed. Amazon.com, Inc. (NASDAQ:AMZN) is one of the stocks Jim Cramer recently discussed.\n\nAmazon.com, Inc. (NASDAQ:AMZN) is almost a daily feature of Cramer\u2019s morning show. With the firm\u2019s roots stretching from retail to high-end technology, the CNBC TV host has plenty to talk about. He continues to believe that Amazon.com, Inc. (NASDAQ:AMZN) is one of the dominant retailers in the industry and can emerge as part of a handful of firms that dominate the landscape in the future. Earlier in the year, he also criticized Amazon.com, Inc. (NASDAQ:AMZN)\u2019s Alexa AI assistant. After the firm\u2019s Prime Day sales event in July, Cramer gushed about the great deals he could find on the website. More recently, his comments have covered the firm\u2019s earnings report, its cloud computing business, and reliance on in-house AI chips as opposed to NVIDIA\u2019s high-performance and pricey GPUs. During this show, Cramer commented on big tech firms in general, and after saying that big tech firms in general were heading in a good direction, he discussed Amazon.com, Inc. (NASDAQ:AMZN) and AI:\n\nJim Cramer Mentions Amazon.com, Inc. (AMZN) & AI\n\n\u201cI mean if I\u2019m Andy Jassy, I\u2019m saying, hmm, I\u2019ve got the new voice AI to talk to Alexa, maybe I got to up my game.\u201d\n\nWhile we acknowledge the potential of AMZN as an investment, our conviction lies in the belief that some AI stocks hold greater promise for delivering higher returns and have limited downside risk. If you are looking for an extremely cheap AI stock that is also a major beneficiary of Trump tariffs and onshoring, see our free report on the best short-term AI stock.\n\nREAD NEXT: 30 Stocks That Should Double in 3 Years and 11 Hidden AI Stocks to Buy Right Now.\n\nDisclosure: None. This article is originally published at\u00a0Insider Monkey.\n\nTerms and Privacy Policy\nPrivacy Dashboard"
    },
    {
        "url": "https://finance.yahoo.com/news/why-amazon-took-tesco-m-160523416.html",
        "title": "Why Amazon took on Tesco, M&S and Sainsbury's - and lost",
        "detail": "Why Amazon took on Tesco, M&S and Sainsbury's - and lost\nJonathan Prynn\nTue, Sep 23, 2025, 9:05 AM 2 min read\nIn this article:\nAMZN\nTSCO.L\nMKS.L\nSBRY.L\nROO.L\nAmazon launched its first Fresh store in Ealing in 2021 (Victoria Jones/PA)\n\nAmazon does not always get to win. That is twice now over recent years that the Seattle behemoth thought it could roll over the incumbents in London - but got it wrong.\n\nNews that all 19 Amazon Fresh stores are to shut down - all but one are based in London - does not come as a huge surprise. In the Standard\u2019s local branch on Moorgate shoppers rarely outnumbered staff, while the food hall in a neighbouring Mark & Spencer was often rammed.\n\nThis admission of defeat comes seven years after Amazon closed its restaurant delivery service. That lasted just two years but never made significant inroads into a sector already dominated by Deliveroo and Uber Eats.\n\nThis time Amazon chose an even tougher nut to crack. Tesco, Sainsbury\u2019s, Asda, Morrison, M&S and Waitrose are formidable long-term operators running on tight margins and with many decades of brand recognition and loyalty behind them.\n\nTesco, Sainsbury, Marks and the Co-op have also carpet bombed London with hundreds of convenience stores.\n\nMore recently the arrival of Aldi and Lidl and their rapid roll-out in London has just made the grocery landscape in the capital even more intensely competitive.\n\nThere was simply no space for Amazon and to be frank very little affection for its rather soulless \u201cJust Walk Out\u201d automatic payment system.\n\nIt may only be the most fleeting of human contacts but it seems the British public get more out of a couple of minutes of interaction at a till than many people assumed.\n\nMy observation, walking past the Amazon Fresh store on a daily basis, was there was almost an aversion to going into a grocery shop named after a tech brand where some shoppers, including myself, were confused about how to pay.\n\nIt is no reflection on the food on offer. On my one visit, the sandwich I bought was perfectly adequate. So why did I never go back?\n\nOf course the closure of fewer than 20 convenience stores in London is hardly likely to keep Jeff Bezos awake at night or worry a \u00a32 trillion company. But it is perhaps a healthy thing that even the usually all conquering Amazon occasionally trips up and falls on its face.\n\nTerms and Privacy Policy\nPrivacy Dashboard"
    },
    {
        "url": "https://finance.yahoo.com/news/amazon-abandons-uk-supermarket-push-145414637.html",
        "title": "Amazon abandons UK supermarket push after struggling to compete",
        "detail": "Amazon abandons UK supermarket push after struggling to compete\nChris Price\nTue, Sep 23, 2025, 7:54 AM 2 min read\nIn this article:\nAMZN\nAmazon first launched the Fresh brand in 2021 - Steve Taylor/SOPA Images/LightRocket via Getty Images\n\nAmazon has abandoned plans to take on Britain\u2019s major supermarket chains in a move putting 250 jobs at risk.\n\nThe tech giant said it would shut all of its 19 Amazon Fresh grocery stores in the UK, although it is planning to convert five of these into Whole Foods Market stores.\n\nBosses said they remained \u201cdeeply invested\u201d in the UK but would instead shift their focus towards their online grocery business.\n\nAmazon first launched the Fresh brand in 2021, opening its first till-less store in Ealing, with technology that allowed customers to walk out with their shopping without having to use a till.\n\nShoppers used an app to enter the store and were then billed when they left, with a range of cameras and other technology used to work out which products they purchased.\n\nHowever, the group slowed down significant growth ambitions for the business, as shopper demand waned at the end of the pandemic.\n\nJohn Boumphrey, from Amazon UK, said: \u201cWe\u2019re deeply invested in the UK\u2019s economic growth and creating opportunities for both customers and employees.\n\n\u201cWe\u2019ll be working hard to support any potentially impacted teams throughout these planned changes and are deeply grateful for their dedication. If the proposal moves forward, we\u2019ll support our employees by offering alternative employment opportunities within Amazon wherever possible.\u201d\n\nShopper demand for Amazon Fresh stores waned at the end of the pandemic - Anthony Upton\n\nThe company, which operates online delivery partnerships with Morrisons, Co-op, Iceland, and Gopuff, has launched a consultation process with the employees affected.\n\nThe move away from physical stores comes as the supermarket sector faces a series of potentially painful reforms to business rates in the upcoming Budget.\n\nIn July, Tesco and Sainsbury\u2019s warned Rachel Reeves that plans for a \u00a31.7bn tax raid on big shops would accelerate the decline of the high street.\n\nThe British Retail Consortium has estimated that changes to business rates, which will increase the surcharge on larger properties, will hit around 4,000 high street stores.\n\nThierry Garnier, the chief executive of Kingfisher, on Tuesday hit out at the Chancellor\u2019s planned overhaul over fears it will benefit online sellers at the expense of larger bricks and mortar retailers.\n\nMr Boumphrey added: \u201cSince 2008, we\u2019ve worked hard to innovate to help our customers save time and money when shopping for groceries and household essentials.\n\n\u201cWe continue to invent and invest to bring more choice and convenience to UK customers, enabling them to shop for a wide range of everyday essentials and groceries with low prices and fast delivery through Amazon.co.uk, Amazon Fresh and Whole Foods Market stores.\u201d\n\nBroaden your horizons with award-winning British journalism. Try The Telegraph free for 1 month with unlimited access to our award-winning website, exclusive app, money-saving offers and more.\n\nTerms and Privacy Policy\nPrivacy Dashboard"
    },
    {
        "url": "https://finance.yahoo.com/news/amazon-abandons-uk-supermarket-push-145414431.html",
        "title": "Amazon abandons UK supermarket push",
        "detail": "Amazon abandons UK supermarket push\nChris Price\nTue, Sep 23, 2025, 7:54 AM 2 min read\nIn this article:\nAMZN\nAmazon first launched the Fresh brand in 2021 - Steve Taylor/SOPA Images/LightRocket via Getty Images\n\nAmazon has abandoned plans to take on Britain\u2019s major supermarket chains in a move putting 250 jobs at risk.\n\nThe tech giant said it would shut all of its 19 Amazon Fresh grocery stores in the UK, although it is planning to convert five of these into Whole Foods Market stores.\n\nBosses said they remained \u201cdeeply invested\u201d in the UK but would instead shift their focus towards their online grocery business.\n\nAmazon first launched the Fresh brand in 2021, opening its first till-less store in Ealing, with technology that allowed customers to walk out with their shopping without having to use a till.\n\nShoppers used an app to enter the store and were then billed when they left, with a range of cameras and other technology used to work out which products they purchased.\n\nHowever, the group slowed down significant growth ambitions for the business, as shopper demand waned at the end of the pandemic.\n\nJohn Boumphrey, from Amazon UK, said: \u201cWe\u2019re deeply invested in the UK\u2019s economic growth and creating opportunities for both customers and employees.\n\n\u201cWe\u2019ll be working hard to support any potentially impacted teams throughout these planned changes and are deeply grateful for their dedication. If the proposal moves forward, we\u2019ll support our employees by offering alternative employment opportunities within Amazon wherever possible.\u201d\n\nShopper demand for Amazon Fresh stores waned at the end of the pandemic - Anthony Upton\n\nThe company, which operates online delivery partnerships with Morrisons, Co-op, Iceland, and Gopuff, has launched a consultation process with the employees affected.\n\nThe move away from physical stores comes as the supermarket sector faces a series of potentially painful reforms to business rates in the upcoming Budget.\n\nIn July, Tesco and Sainsbury\u2019s warned Rachel Reeves that plans for a \u00a31.7bn tax raid on big shops would accelerate the decline of the high street.\n\nThe British Retail Consortium has estimated that changes to business rates, which will increase the surcharge on larger properties, will hit around 4,000 high street stores.\n\nThierry Garnier, the chief executive of Kingfisher, on Tuesday hit out at the Chancellor\u2019s planned overhaul over fears it will benefit online sellers at the expense of larger bricks and mortar retailers.\n\nMr Boumphrey added: \u201cSince 2008, we\u2019ve worked hard to innovate to help our customers save time and money when shopping for groceries and household essentials.\n\n\u201cWe continue to invent and invest to bring more choice and convenience to UK customers, enabling them to shop for a wide range of everyday essentials and groceries with low prices and fast delivery through Amazon.co.uk, Amazon Fresh and Whole Foods Market stores.\u201d\n\nTerms and Privacy Policy\nPrivacy Dashboard"
    },
    {
        "url": "https://finance.yahoo.com/news/estee-lauder-online-sales-hit-145200867.html",
        "title": "Estee Lauder Online Sales Hit 31%: Structural Shift in Beauty Retail?",
        "detail": "Estee Lauder Online Sales Hit 31%: Structural Shift in Beauty Retail?\nZacks Equity Research\nTue, Sep 23, 2025, 7:52 AM 4 min read\nIn this article:\nLSF\nSBH\nEL\nAMZN\n\nThe Estee Lauder Companies Inc. (EL) is seeing a meaningful digital acceleration. In fiscal 2025, online sales accounted for 31% of total sales, a record level and 3 percentage points higher than last year. This marks more than just incremental progress. It indicates a structural pivot in how consumers are engaging with prestige beauty.\n\nSeveral factors underpinned this shift. The company expanded its presence across Amazon\u2019s Premium Beauty stores, where 11 brands are now available in the United States and three in Canada. Southeast Asia also became a proving ground, with Estee Lauder leveraging Shopee and TikTok Shop, while its presence on Tmall and Douyin provided steady momentum. Importantly, the company is experimenting with new formats such as AI-powered flagship stores in China, showing a willingness to test innovative retail technology alongside channel expansion.\n\nOnline momentum accelerated in the back half of fiscal 2025, with organic sales growth improving from low single digits in the first half to mid-single digits in the second half. Management noted that the mix is expected to climb further, with digital being a core driver of growth. The company\u2019s online strength also helps offset the structural decline in travel retail, which fell to just 15% of sales in fiscal 2025, down 4 percentage points from 2024 and sharply from pandemic-era highs.\n\nAs online sales rise to nearly a third of the business, Estee Lauder\u2019s sales mix is undergoing a notable transformation. The shift underscores the company\u2019s efforts to broaden consumer access through multiple digital platforms, while also reducing exposure to more volatile channels. Whether this balance sustains long-term will be an area to watch in the coming years.\n\nEstee Lauder\u2019s Share Price Performance\n\nShares of this Zacks Rank #3 (Hold) company have gained 13.3% in the past three months against the broader Consumer Staples sector\u2019s 3.8% decline. EL has also outperformed the industry and the S&P 500 index\u2019s growth of 9% and 11.3%, respectively, during the same period.\n\nEL Stock's Past Three Months Performance\nZacks Investment Research\n\n\nImage Source: Zacks Investment Research\n\nUnlocking Estee Lauder\u2019s Valuation\n\nEstee Lauder currently trades at a forward 12-month P/E ratio of 39.38 compared with the industry average of 27.43 and the sector\u2019s 16.48. This valuation places the stock at a premium relative to peers, indicating broader market expectations around its business stability and ability to navigate current cost and demand dynamics.\n\nEstee Lauder Valuation Picture\nZacks Investment Research\n\n\nImage Source: Zacks Investment Research\n\nStory Continues\nTerms and Privacy Policy\nPrivacy Dashboard"
    },
    {
        "url": "https://finance.yahoo.com/news/fold-teaming-stripe-bitcoin-rewards-135413230.html",
        "title": "Fold Teaming With Stripe for Its Bitcoin Rewards Credit Card",
        "detail": "Fold Teaming With Stripe for Its Bitcoin Rewards Credit Card\nWill Canny\nTue, Sep 23, 2025, 6:54 AM 1 min read\nIn this article:\nBTC-USD\nSTRI.PVT\nV\nAMZN\nTGT\n\nNasdaq-listed Fold (FLD) said it was teaming up with Stripe and Visa (V) to launch its first bitcoin-only rewards credit card, giving users a simple way to stack sats on everyday purchases.\n\nThe Fold Bitcoin Credit Card will run on Visa\u2019s network and use Stripe Issuing\u2019s infrastructure, the company said in the Tuesday press release.\n\nInvest in Gold\nAmerican Hartford Gold: #1 Precious Metals Dealer in the Nation\nLearn More\nThor Metals Group: Best Overall Gold IRA\nLearn More\nPriority Gold: Up to $15k in Free Silver + Zero Account Fees on Qualifying Purchase\nLearn More\nPowered by Money.com - Yahoo may earn commission from the links above.\n\nFold shares were 10% lower at publication time, trading $3.49.\n\nCardholders will earn 2% back in bitcoin instantly, with an extra 1.5% boost available when paying off purchases via a Fold Checking Account with qualified activity.\n\nFold says shoppers can also earn up to 10% back with top retail partners, including Amazon, Target, Home Depot, Starbucks, and Uber.\n\nOur credit card offers clear and compelling value and makes bitcoin easily accessible to everyone,\u201d said Will Reeves, Fold\u2019s CEO and founder, in the release.\n\n\u201cThere are no categories to manage, no tokens to stake, no exchange account or balance requirements; just real bitcoin, earned automatically with every purchase,\" Reeves added.\n\nStripe called the partnership a milestone for its new consumer card-issuing product, designed to let fintechs bring innovative payment tools to market without managing their own infrastructure.\n\nVisa\u2019s crypto lead Cuy Sheffield said the collaboration gives consumers \u201ca safe, simple way to earn bitcoin as they shop.\u201d\n\nFold, which already offers a bitcoin debit card, exchange, and gift card program, has processed over $3.1 billion in transactions and distributed more than $83 million in bitcoin rewards to date.\n\nThe credit card, the company says, is the next step in building a full suite of bitcoin-native financial services.\n\nFold holds almost 1,500 bitcoin in its treasury.\n\nRead more: Fold Holdings Slumps 7% on Delay in Bitcoin Rewards Credit Card\n\nTerms and Privacy Policy\nPrivacy Dashboard"
    },
    {
        "url": "https://finance.yahoo.com/news/hasbro-women-innovators-play-returns-130000125.html",
        "title": "Hasbro Women Innovators of Play Returns for Third Annual Virtual Event and Challenge",
        "detail": "This is a paid press release. Contact the press release distributor directly with any inquiries.\nHasbro Women Innovators of Play Returns for Third Annual Virtual Event and Challenge\nBusiness Wire\nTue, Sep 23, 2025, 6:00 AM 4 min read\nIn this article:\nHAS\nAMZN\nTGT\n\nProgram Continues as Global Destination for Women Innovators with Expanded Programming featuring Industry Leaders from Scopely, Amazon, Target, and IDEO\n\nPAWTUCKET, R.I., September 23, 2025--(BUSINESS WIRE)--Hasbro, Inc. (NASDAQ: HAS), a leading games, IP, and toy company, today announced its Hasbro Women Innovators of Play 2025 lineup of events to celebrate and connect women toy and game innovators worldwide. The third annual program launches on October 9, 2025, building on the remarkable success of 2024.\n\nHasbro's Women Innovators of Play launched in Fall 2023 to inspire the next generation of women and girls to unleash their creativity and increase awareness and exposure to creative career paths.\n\n\"At Hasbro, we\u2019re driven by a powerful mission: to spark joy and foster community through the magic of play. Through our Playing to Win strategy, we\u2019re proud to be opening more doors for women and girls in the toy and game industry,\" said Kim Boyd, President, Licensing & Entertainment. \"The enthusiasm surrounding our Women Innovators of Play program has been truly inspiring\u20142024 saw double the registrations compared to the prior year, with participants joining from all corners of the world. This year\u2019s program unites trailblazing industry leaders who are redefining the future of play and imagination.\"\n\nHasbro's 2024 Challenge saw over 100 submissions from women innovators globally. Submissions were judged on innovation, mass marketability, fun factor and playability, design and aesthetics, and manufacturability. The three winners \u2013 Elise Hardman, Amelie Le-Roche, and Natalie Podd \u2013 each received a prize of $10,000 USD and visits to Hasbro offices for networking and mentorship sessions with Hasbro women leaders.\n\n2025 Program Features Leading Women Innovators\n\nThis year\u2019s free, 90-minute virtual program will feature conversations and panels with industry leaders, including Eunice Lee, COO of Scopely; executives from Amazon, Target, and IDEO; and Hasbro leaders. Sessions will cover leadership insights, retail trends, product design, and the future of gaming.\n\nKey sessions include:\n\n\"Lessons in Leadership, Fandom, and the Future of Play\" with Eunice Lee (COO, Scopely) and Roberta Thomson (CEO of AI Studio, Hasbro).\n\n\"Shop Talk: Power Dynamics, Pivoting, and the Female POV\" featuring Christina Jansa (VP \u2013 Toys, Target), Anne Carrihill (Director \u2013 Toys & Games, Amazon), Greta Carey (Director \u2013 Digital Marketing & Sales, Card Kingdom), and Lisa Gilbert (President \u2013 NA & LATAM Commercial Sales, Hasbro) \u2013 moderated by Ali Mierzejewski (Editor-in-Chief of The Toy Insider).\n\n\"From Sketchbook to Shelf\" with Liz DeSilva (Chief Creative Officer, Whatever! Company), Vlasta Komorous-King (Senior Design Director, IDEO), and Jodi Bondi Norgaard (Toy Designer) \u2013 moderated by Vivian Nguyen (Associate Principal Product Designer, Hasbro).\n\nStory Continues\nTerms and Privacy Policy\nPrivacy Dashboard"
    },
    {
        "url": "https://finance.yahoo.com/news/amazon-com-close-amazon-fresh-125158778.html",
        "title": "Amazon.com to close all of its Amazon Fresh UK stores",
        "detail": "Amazon.com to close all of its Amazon Fresh UK stores\nReuters\nUpdated Tue, Sep 23, 2025, 6:07 AM 1 min read\nIn this article:\nAMZN\n\nLONDON (Reuters) -Amazon.com (AMZN) said it planned to close all of its 19 Amazon Fresh UK convenience grocery stores, of which five would be converted to its Whole Foods Markets brand, less than five years after it entered the market.\n\nAmazon Fresh pioneered \"walk out\" technology in Britain, enabling customers to skip the checkout line when they picked up groceries, including its own \"by Amazon\" brand.\n\nIt said on Tuesday it had taken the difficult decision to propose closing the stores after evaluating the business and the substantial growth opportunities in online delivery.\n\nIt said it was seeing strong demand for household essentials and groceries from its Amazon.co.uk store, Amazon Fresh online, Whole Foods Market and its online delivery partnerships with Morrisons, Co-op, Iceland and Gopuff.\n\nNext year it said it planned to introduce perishable groceries alongside everyday essentials and other products on Amazon.co.uk with same-day delivery.\n\nIn addition to expanding online grocery, it said it would convert five Amazon Fresh locations to Whole Foods Market, the U.S. chain it bought in 2017.\n\n(Reporting by Paul Sandle; editing by Sarah Young)\n\nTerms and Privacy Policy\nPrivacy Dashboard"
    },
    {
        "url": "https://finance.yahoo.com/news/full-alliance-group-delivers-record-120500193.html",
        "title": "Full Alliance Group Delivers Record Q3 Performance with Amazon Launch, and International Expansion",
        "detail": "This is a paid press release. Contact the press release distributor directly with any inquiries.\nFull Alliance Group Delivers Record Q3 Performance with Amazon Launch, and International Expansion\nFull Alliance Group, Inc.\nTue, Sep 23, 2025, 5:05 AM 3 min read\nIn this article:\nFAGI\nAMZN\n\nTampa-based company achieves triple milestone quarter with contract manufacturing surge with over 155,000 units, doctor-endorsed consumer brand debut, and first European agricultural order\n\nTAMPA, FL / ACCESS Newswire / September 23, 2025 / Full Alliance Group, Inc. (OTCID:FAGI) today reported exceptional third-quarter momentum across all business segments, with its wholly owned subsidiary Aquaox Pure Solutions achieving three major milestones: record contract manufacturing volume of 155,000 units, the successful Amazon launch of its doctor-endorsed JUSSPRAY\u2122 consumer brand, and the company's first international agricultural contract.\n\nRecord Contract Manufacturing Drives Q3 Growth\n\nAquaox Pure secured purchase orders exceeding 155,000 units this quarter through its expanding contract manufacturing division, representing significant growth in demand from health, beauty, and wellness industry partners. The diverse order portfolio spans multiple product formats, from convenient 2 oz travel bottles to 1 Gallon sizes, demonstrating the flexibility and scalability of the company's manufacturing capabilities.\n\nAll production takes place at Aquaox Pure's state-of-the-art 25,000 square-foot GMP-certified facility in Tampa, which combines cutting-edge electro-chemical activation nano-bubble technology to deliver both superior product quality and environmentally responsible manufacturing.\n\nJUSSPRAY\u2122 Achieves Amazon Milestone with Medical Endorsement\n\nBuilding on its manufacturing success, Aquaox Pure launched its proprietary consumer brand JUSSPRAY\u2122 direct to consumers via Amazon. The innovative product delivers hospital-grade antimicrobial protection through a gentle, pH-balanced formulation safe for sensitive skin and children.\n\nThe launch gained significant credibility through the endorsement of board-certified Vascular surgeon and renowned Anti-Aging expert Richard M. Goldfarb, MD, FACS, who has designated JUSSPRAY\u2122 as \"Doctor Recommended and Doctor Approved,\" praising it as a scientifically backed solution for everyday skin protection.\n\nJUSSPRAY\u2122 Key Differentiators:\n\nAdvanced Formula: Alcohol-free, eco-friendly solution powered by naturally derived hypochlorous acid (HOCl) and proprietary nanobubble technology\n\nSafety Validated: Doctor Approved and approved for safe daily use across all age groups\n\nSustainable Design: Environmentally conscious packaging available in multiple convenient sizes\n\nVisit Amazon Store\n\nVisit Website\n\nInternational Expansion Begins with European Agricultural Contract\n\nAquaox Pure achieved another strategic milestone by securing its first international purchase order from a Spanish agricultural partner. This specialized contract involves HOCl solutions designed for livestock umbilical cord cleansing, providing effective bacterial growth reduction and infection prevention. The agreement validates the broad applicability of Aquaox's technology across both human and veterinary health markets, opening significant opportunities for global expansion.\n\nWeiterlesen\nAGB und Datenschutzerkl\u00e4rung\nPrivacy Dashboard"
    },
    {
        "url": "https://finance.yahoo.com/news/tesla-tops-mag-7-group-120000566.html",
        "title": "Tesla Tops Mag-7 Group in a Month: ETFs in Focus",
        "detail": "Tesla Tops Mag-7 Group in a Month: ETFs in Focus\nSanghamitra Saha\nTue, Sep 23, 2025, 5:00 AM 3 min read\nIn this article:\nTESL\nFDIS\nXLY\nTSLA\nAMZN\n\nTesla TSLA shares have gained 25.3% over the past month (as of Sept. 22, 2025). Alphabet GOOGL shares have jumped 21.1%, while Apple AAPL, Microsoft MSFT, Meta META and NVIDIA NVDA have added 12%, 2%, 1.6% and 2%, respectively, during the same timeframe. Amazon AMZN, however, has slipped 0.1% over the past one month.\n\nWhat\u2019s Behind the Rally?\n\nTesla\u00a0recently grabbed headlines after CEO Elon Musk scooped up $1 billion worth of company shares. Retail investors cheered it as a vote of confidence. Agreed, Tesla\u2019s core electric vehicle (EV) business is not doing great. But the company is striving to emerge as an artificial intelligence behemoth.\n\nTesla focuses on autonomous driving and robotics. It has recently received approval to begin testing its robotaxi, an autonomous driving ride-hailing service in Arizona, as quoted on an investors.com article.\n\nThe investors.com article went on to highlight that Nevada's Department of Motor Vehicles also gave the green signal to Tesla\u2019s plans for testing its robotaxi service in the state. Tesla launched its robotaxi service in late June in Austin, TX. The ride-hailing operation expanded to the San Francisco Bay Area, with safety drivers, the article indicated.\n\nTesla Ramps Up Output in Giga Berlin\n\nTesla\u2019s Giga Berlin plant in Gr\u00fcnheide is gearing up for a production boost through the remainder of 2025 amid growing demand, per Germany's DPA news agency, as quoted on Economic Times. The good sales figures are coming in even as Tesla faces stiff competition from Chinese peers in Europe.\n\nTesla to Report Record Deliveries Data?\n\nTesla stock lately received another boost as\u00a0Piper Sandler\u00a0analyst Alex Potter maintained an Overweight rating and raised its\u00a0price forecast from $400 to $500, as quoted on Benzinga. Potter landed on this target price after a research trip to China, where he met with electric vehicle makers.\n\nThe analyst said that although Chinese automakers pose huge competition to Tesla, the U.S. EV behemoth has an edge over them when it comes to \"real-world AI,\" as quoted on the same Benzinga article. Benzinga went on to highlight that the analyst anticipated Tesla to deliver about 495,000 units in the third quarter, probably setting a record.\n\nAny Wall of Worry?\n\nTesla is apparently a pricey stock. It is trading at a massively higher valuation compared with the Automotive \u2013 Domestic industry. \u00a0Many AI-heavy Mag-7 members, including NVIDIA, do not boast as high a P/E (TTM) as Tesla.\n\nPlus, Piper Sandler analyst Alex Potter is also less certain about Tesla's 2026 prospect, when Tesla targets 1.9 million units (as quoted on the above-mentioned Benzinga article).\n\nStory Continues\nTerms and Privacy Policy\nPrivacy Dashboard"
    },
    {
        "url": "https://finance.yahoo.com/news/amazon-fresh-locations-stores-planned-120000184.html",
        "title": "Amazon Fresh: Locations of stores planned to close",
        "detail": "Amazon Fresh: Locations of stores planned to close\nHenry Saker-Clark\nTue, Sep 23, 2025, 5:00 AM 1 min read\nIn this article:\nAMZN\n\nAmazon (AMZN) has revealed plans to shut all of its UK Amazon Fresh grocery stores in a move which will see the brand leave the high street after four years.\n\nThe business expanded to 19 sites across London but said on Tuesday that it is now proposing to close all stores.\n\nFive of the stores could however reopen under the retail giant\u2019s Whole Foods Market brand.\n\nAmazon Fresh grocery stores in the UK will close (Victoria Jones/PA)\n\nIt is understood that around 250 staff work across the Amazon Fresh stores, although it is understood that not all workers will be affected.\n\nHere are the locations of the Amazon Fresh stores, which are all currently set to close:\n\nAldgate, Greater London\nAngel, Greater London\nChingford, Greater London\nEast Croydon, Greater London\nEuston, Greater London\nHolborn, Greater London\nHounslow, Greater London\nHoxton, Greater London\nKensington, Greater London\nLiverpool Street, Greater London\nMoorgate, Greater London\nMonument, Greater London\nNotting Hill Gate, Greater London\nSouthwark, Greater London\nSevenoaks, Greater London\nWembley, Greater London\nWest Hampstead, Greater London\nWhite City, Greater London\nWood Wharf, Greater London\n\nTerms and Privacy Policy\nPrivacy Dashboard"
    },
    {
        "url": "https://finance.yahoo.com/news/jobs-risk-amazon-fresh-grocery-120000887.html",
        "title": "Jobs at risk as all Amazon Fresh grocery shops set to close",
        "detail": "Jobs at risk as all Amazon Fresh grocery shops set to close\nHenry Saker-Clark\nTue, Sep 23, 2025, 5:00 AM 2 min read\nIn this article:\nAMZN\n\nAmazon (AMZN) has revealed plans to close all of its Amazon Fresh grocery stores in the UK, putting up to 250 workers at the retailer at risk.\n\nThe US-based firm said it plans to shut its 19 Amazon Fresh stores, but is proposing to convert five of these into Whole Foods stores.\n\nIt said the move is part of a wider overhaul of its UK grocery operations which will shift focus more towards its online business, with bosses saying that it is still \u201cdeeply invested\u201d in the UK.\n\nAmazon said on Tuesday that it has now launched a consultation process proposing the closure of the Amazon Fresh UK stores.\n\nAmazon Fresh launched its first UK store in Ealing in 2021 (Victoria Jones/PA)\n\nIt is consulting with employees at the sites, which employ around 250 staff.\n\nHowever, it said not all workers are set to be impacted and it plans to offer affected employees new roles in other parts of the business.\n\nAmazon first launched the Fresh brand in 2021, opening its first till-less store in Ealing, with technology that allowed customers to walk out with their shopping without having to use a till.\n\nShoppers used an app to enter the store and were then billed to the platform when they left, with a range of cameras and other technology used to work out which products they purchased.\n\nHowever, the group slowed down significant growth ambitions for the business as shopper demand waned at the end of the coronavirus pandemic.\n\nAs part of the proposals, the company is seeking to convert five of the 19 stores to its Whole Foods Market brand, which focuses on organic produce.\n\nIt said the conversion plans and two further new sites are expected to grow the Whole Foods business to 12 stores by the end of next year.\n\nAmazon used its \u2018Just Walk Out Technology\u2019 in the stores (Lia Toby/PA)\n\nOn Tuesday, Amazon also said it plans to double the number of Prime subscription members with access to at least three of the retailer\u2019s grocery options, through its partners Morrisons, Iceland, Co-op and Gopuff.\n\nIt also said it will introduce fresh groceries including dairy, meat and seafood to Amazon.co.uk from next year.\n\nJohn Boumphrey, country manager for Amazon UK, said: \u201cSince 2008, we\u2019ve worked hard to innovate to help our customers save time and money when shopping for groceries and household essentials.\n\n\u201cWe continue to invent and invest to bring more choice and convenience to UK customers, enabling them to shop for a wide range of everyday essentials and groceries with low prices and fast delivery through Amazon.co.uk, Amazon Fresh, and Whole Foods Market stores, alongside our third-party grocery partners, including Morrisons, Co-op, Iceland, and Gopuff.\u201d\n\nCondiciones y Pol\u00edtica de privacidad\nPrivacy Dashboard"
    },
    {
        "url": "https://finance.yahoo.com/news/canada-hopes-trump-100-000-120000915.html",
        "title": "Canada Hopes Trump\u2019s $100,000 Visa Fee Redirects Talent North",
        "detail": "Canada Hopes Trump\u2019s $100,000 Visa Fee Redirects Talent North\nCurtis Heinzl\nTue, Sep 23, 2025, 5:00 AM 5 min read\nIn this article:\nAMZN\nMSFT\nGOOGL\n\nA worker inspects Bitcoin mining machines at a computation center in Joliette, Quebec.\n\n(Bloomberg) -- For years, Canada\u2019s highly-skilled industries such as technology and health care have suffered a brain drain to the US. Some executives believe President Donald Trump\u2019s move to make H-1B visas more expensive will change the dynamic.\n\nMost Read from Bloomberg\n\nTrump Cancels Trail, Bike-Lane Grants Deemed \u2018Hostile\u2019 to Cars\n\nOver 5,000 NYC Rent-Stabilized Apartments Headed for Auction\n\nShould We Let Public Transit Die?\n\nTenants Seek to Unionize One Private Equity Firm's Entire Housing Portfolio\n\nWhere Modern Art Meets Wild Prairie\n\nTrump signed an executive order Friday imposing $100,000 fees on new H-1Bs, creating confusion and frustration for companies that rely on the program to bring in global talent in computer programming, engineering and other roles.\n\nThe fee is a significant opportunity for Canada, according to some tech industry players, at a time when the country is seeking answers to low productivity growth and the economic drag of US tariffs.\n\n\u201cCities like Vancouver or Toronto will thrive instead of American cities,\u201d Garry Tan, CEO of famed San Francisco startup incubator Y Combinator, which has helped start Airbnb Inc. and Stripe Inc., said in a post on X. Trump\u2019s policy is a \u201cmassive gift to every overseas tech hub\u201d by erecting a \u201ctoll booth\u201d for smaller US firms to hire talent, he said in the post, which was later deleted.\n\nCompanies including Amazon.com Inc., Microsoft Corp. and Alphabet Inc. already maintain offices in major Canadian cities and could accelerate hiring there to skirt the US fee \u2014 while also paying lower salaries than those south of the border. Amazon had more than 8,500 corporate and technology employees in its tech hubs in Vancouver and Toronto as of a year ago, according to information disclosed by the company. Microsoft had 2,700 staff in a development hub in Vancouver as of April.\n\nDuring a speech in New York on Monday, Prime Minister Mark Carney observed that Canada\u2019s universities are some of the biggest producers of talented graduates in artificial intelligence and quantum computing, but \u201cmost of them go to the United States.\u201d\n\nThen he added: \u201cI understand you\u2019re changing your visa policy here, so we\u2019re going to hang on to a few of those.\u201d\n\nCurrently, the world\u2019s top computer science schools funnel graduates into American tech hubs, thanks in part to H-1B sponsorships. Canadian citizens in many professions have an easier route through so-called \u201cTN visas\u201d under the US-Mexico-Canada Agreement.\n\nHigher salaries and better weather are part of the attraction for Canadian-educated engineers. The median tech worker earns 46% more in the US than in Canada, according to a 2023 report from The Dais, a public policy and leadership think tank at Toronto Metropolitan University.\n\nStory Continues\nTerms and Privacy Policy\nPrivacy Dashboard"
    },
    {
        "url": "https://finance.yahoo.com/news/market-chatter-amazon-com-trial-112122866.html",
        "title": "Market Chatter: Amazon.com Trial Starts on Claims by US FTC of Deceiving Prime Subscribers",
        "detail": "PREMIUM\nMarket Chatter: Amazon.com Trial Starts on Claims by US FTC of Deceiving Prime Subscribers\nMT Newswires\nTue, Sep 23, 2025, 4:21 AM 1 min read\nIn this article:\nAMZN\n\nAmazon.com (AMZN) and three of its executives will be under trial in Seattle from Tuesday over claim\n\nPREMIUM\nUpgrade to read this MT Newswires article and get so much more.\nA Silver or Gold subscription plan is required to access premium news articles.\nUpgrade\nAlready have a subscription? Sign in\nTerms and Privacy Policy\nPrivacy Dashboard"
    },
    {
        "url": "https://finance.yahoo.com/news/best-stock-buy-now-amazon-111500896.html",
        "title": "Best Stock to Buy Right Now: Amazon vs. MercadoLibre",
        "detail": "Best Stock to Buy Right Now: Amazon vs. MercadoLibre\nWill Healy, The Motley Fool\nTue, September 23, 2025 at 4:15 AM MST 5 min read\nIn this article:\nMELI\nAMZN\nKey Points\n\nMercadoLibre is less than 5% of Amazon's size as measured by market cap.\n\nAmazon has driven faster profit growth so far this year despite its much larger size.\n\nMercadoLibre far outpaced Amazon's revenue growth, but does that justify its higher earnings multiple?\n\n10 stocks we like better than MercadoLibre \u203a\n\nUnderstandably, Amazon (NASDAQ: AMZN) and MercadoLibre (NASDAQ: MELI) are often compared to one another. Both companies pioneered e-commerce in different parts of the world and then went on to spearhead new industries. Those businesses were distinct but also natural outgrowths of their e-commerce operations.\n\nAdmittedly, since it has traded for 10 years longer, Amazon has delivered higher total returns than MercadoLibre. However, MercadoLibre has had the edge in the time that both stocks have traded. Thus, investors comparing the two may wonder whether Amazon or MercadoLibre is the best stock to buy right now.\n\nImage source: Getty Images.\nThe case for Amazon\n\nAmazon's nearly $2.5 trillion market cap might lead investors to question whether its days of rapid growth are over. Amid such a massive size, higher-percentage growth becomes a more difficult feat mathematically.\n\nNonetheless, part of Amazon's genius has involved circumventing this problem by serving as an umbrella for several smaller but faster-growing businesses. Its online stores business remains its largest revenue source, though the low margins make it unclear whether that is a profitable enterprise to this day.\n\nInstead, it derives the majority of its operating income from cloud computing enterprise Amazon Web Services (AWS). On the e-commerce side, the faster growth comes from asset-light businesses such as digital advertising, third-party seller services, and subscriptions.\n\nThose enterprises have also benefited from Amazon's move into artificial intelligence (AI). AI runs many of AWS' workloads. It also helps enable supply chain efficiencies, product placement, and customer service on the e-commerce side of the business. Such improvements should bring Amazon more business and are likely helping its financials already.\n\nIn the first half of 2025, revenue of $323 billion grew 11% compared to year-ago levels. This may lag growth rates of the past. Still, since it kept cost and expense growth in check, the $35 billion in net income for the period was a 48% increase.\n\nSo far this year, the stock is up by about 5%. Nonetheless, in recent years, its valuation has fallen. With its 35 P/E ratio being just above the S&P 500 average of 31, Amazon is becoming an increasingly attractive value.\n\nStory Continues\nTerms and Privacy Policy\nPrivacy Dashboard"
    }
]