[
    {
        "url": "https://finance.yahoo.com/news/bofa-unveils-top-10-u-161255623.html",
        "title": "BofA unveils its top 10 U.S. ideas for Q1 2026"
    },
    {
        "url": "https://finance.yahoo.com/news/equity-allocations-decline-cash-commodities-135141151.html",
        "title": "Equity allocations decline as cash, commodities gain favor, BofA says"
    },
    {
        "url": "https://finance.yahoo.com/news/equities-boost-robust-earnings-2026-133438956.html",
        "title": "Equities to Get Boost From Robust Earnings in 2026 But Near-Term Fed Path Uncertain, Analysts Say"
    },
    {
        "url": "https://finance.yahoo.com/news/wall-street-bulls-roar-again-130700324.html",
        "title": "Wall Street Bulls to Roar Again in 2026: 3 Beaten-Down Stock Picks"
    },
    {
        "url": "https://finance.yahoo.com/news/stocks-to-watch-2026-investing-060027382.html",
        "title": "Stocks to watch in 2026"
    },
    {
        "url": "https://finance.yahoo.com/news/brian-moynihan-says-us-economy-223025746.html",
        "title": "Brian Moynihan Says US Economy Is 'Much Bigger' Than Fed: 'There's Too Much Fascination...'"
    },
    {
        "url": "https://finance.yahoo.com/news/3-stocks-50-warren-buffett-135823017.html",
        "title": "These 3 Stocks Make Up 50% of Warren Buffett\u2019s Portfolio"
    },
    {
        "url": "https://finance.yahoo.com/news/why-bofa-buy-rating-teradyne-112923280.html",
        "title": "Here\u2019s Why BofA Has a Buy Rating on Teradyne, Inc. (TER)"
    },
    {
        "url": "https://finance.yahoo.com/news/expect-stocks-2026-050200562.html",
        "title": "What to expect from stocks in 2026"
    },
    {
        "url": "https://finance.yahoo.com/news/fed-cut-pause-finance-stocks-192600693.html",
        "title": "Will the Fed Cut or Pause? These Finance Stocks Can Win Either Way"
    },
    {
        "url": "https://finance.yahoo.com/news/bofa-bullish-ocular-therapeutix-ocul-162525681.html",
        "title": "BofA Bullish on Ocular Therapeutix (OCUL) as AXPAXLI Targets Superiority Label and Faster Regulatory Path in Wet AMD"
    },
    {
        "url": "https://finance.yahoo.com/news/warren-buffett-says-goodbye-today-131537674.html",
        "title": "Warren Buffett Says Goodbye Today With 65% of Berkshire Hathaway in 5 of His Favorite Stocks"
    },
    {
        "url": "https://finance.yahoo.com/news/zacks-analyst-blog-highlights-bank-120700109.html",
        "title": "The Zacks Analyst Blog Highlights Bank of America, Wells Fargo and U.S. Bancorp"
    },
    {
        "url": "https://finance.yahoo.com/news/bofa-cuts-abbvie-abbv-target-230740908.html",
        "title": "BofA Cuts AbbVie (ABBV) Target While Maintaining Neutral View"
    },
    {
        "url": "https://finance.yahoo.com/news/gen-z-may-not-able-163941824.html",
        "title": "Gen Z may not be able to afford a house or the cost of living\u2014but give it 10 years. They\u2019re on track to gain $36T and become the richest generation"
    },
    {
        "url": "https://finance.yahoo.com/news/warren-buffett-retire-dump-berkshire-162844958.html",
        "title": "Warren Buffett Is About to Retire. Should You Dump Your Berkshire Hathaway (BRK-B) Stock?"
    }
]