[
    {
        "url": "https://finance.yahoo.com/news/reddit-benefits-shift-ai-driven-131008872.html",
        "title": "Reddit benefits from shift to AI-driven answers, says Needham"
    },
    {
        "url": "https://finance.yahoo.com/news/1-mooning-stock-own-decades-043500228.html",
        "title": "1 Mooning  Stock to Own for Decades and 2 We Find Risky"
    },
    {
        "url": "https://finance.yahoo.com/news/reddit-emerges-ai-search-winner-172323768.html",
        "title": "Reddit Emerges as AI Search Winner"
    },
    {
        "url": "https://finance.yahoo.com/news/reddit-inc-nyse-rddt-stock-110030494.html",
        "title": "Reddit, Inc.'s (NYSE:RDDT) Stock Has Shown A Decent Performance: Have Financials A Role To Play?"
    },
    {
        "url": "https://finance.yahoo.com/news/needham-reiterates-buy-reddit-rddt-074737669.html",
        "title": "Needham Reiterates Buy on Reddit (RDDT), Calls It a \u201cBest Idea for 2026\u201d"
    },
    {
        "url": "https://finance.yahoo.com/news/10m-retire-early-couple-did-213142286.html",
        "title": "Some Say You Need $10M To Retire Early, But This Couple Did It With $1M. Now Their Monthly Expenses Are Just $1,241"
    },
    {
        "url": "https://finance.yahoo.com/news/reddit-rddt-valuation-check-strong-041959831.html",
        "title": "Reddit (RDDT) Valuation Check After Strong Recent Share Price Momentum"
    },
    {
        "url": "https://finance.yahoo.com/news/just-got-fired-decide-roll-112200615.html",
        "title": "I Just Got Fired and Need To Decide\u2014Should I Roll My 401(k) Into an IRA or Wait?"
    },
    {
        "url": "https://finance.yahoo.com/news/bytedance-plans-spend-23b-ai-112015475.html",
        "title": "ByteDance plans to spend $23B on AI in 2026, FT reports"
    },
    {
        "url": "https://finance.yahoo.com/news/polymarket-points-finger-third-party-103730407.html",
        "title": "Polymarket Points Finger to Third-Party Provider in Multiple Account Hack"
    },
    {
        "url": "https://finance.yahoo.com/news/1-surging-stock-promising-prospects-043234960.html",
        "title": "1 Surging  Stock with Promising Prospects and 2 We Find Risky"
    },
    {
        "url": "https://finance.yahoo.com/news/rddt-rides-solid-arpu-growth-165700722.html",
        "title": "RDDT Rides on Solid ARPU Growth: Is the Growth Thesis Strengthening?"
    },
    {
        "url": "https://finance.yahoo.com/news/got-5-000-3-tech-145500696.html",
        "title": "Got $5,000? 3 Tech Stocks to Buy and Hold for the Long Term"
    },
    {
        "url": "https://finance.yahoo.com/news/us-high-growth-tech-3-113807289.html",
        "title": "US High Growth Tech: 3 Stocks to Watch"
    },
    {
        "url": "https://finance.yahoo.com/news/seal-skin-covers-reviews-most-100000959.html",
        "title": "Seal Skin Covers Reviews the Most Important Aspect of Outdoor Protection: Fit"
    },
    {
        "url": "https://finance.yahoo.com/news/1-mooning-stock-long-term-043901391.html",
        "title": "1 Mooning  Stock for Long-Term Investors and 2 We Turn Down"
    }
]