[
    {
        "url": "https://finance.yahoo.com/news/top-dividend-stock-just-joined-164700730.html",
        "title": "This Top Dividend Stock Just Joined Meta, Tesla, Broadcom, and Berkshire Hathaway in the $1 Trillion Club",
        "detail": "This Top Dividend Stock Just Joined Meta, Tesla, Broadcom, and Berkshire Hathaway in the $1 Trillion Club\nJennifer Saibil, The Motley Fool\nThu, February 12, 2026 at 8:47 AM PST 4 min read\nIn this article:\nMETA\nTSLA\nAVGO\nBRK.A\nWMT\n\nThe newest member of the $1 trillion market club isn't a surprise. Walmart (NASDAQ: WMT) became a part of this hallowed institution last week, joining a select cadre of mostly tech stocks. But it did so in a more traditional way -- as a leading retail chain that just keeps getting better.\n\nAlthough it recently switched from the New York Stock Exchange (NYSE) to the Nasdaq in a bid to shine a light on its tech prowess, the company still uses a traditional retailing model, and it's the only Dividend King that has made the cut to reach this exclusive club.\n\nWhere to invest $1,000 right now? Our analyst team just revealed what they believe are the 10 best stocks to buy right now, when you join Stock Advisor.\u00a0See the stocks \u00bb\n\nHere's why Walmart is still so powerful after all these years, and why it should continue for many more.\n\nImage source: Walmart.\nEveryone's retailer\n\nWhile Walmart is a discount retailer, some of its recent growth is due to expanding to a wider clientele. It has done this in a number of ways, starting with a stellar e-commerce platform. E-commerce sales increased 27% year over year in the 2026 fiscal third quarter (ended Oct. 31), driving a 5.8% increase in total revenue.\n\nWalmart has an edge over Amazon in at least one way, which is its 4,700-strong store base, which doubles as a distribution hub. It can get orders out fast from stores, and it also appeals to customers who prefer store pickup for their digital orders, especially in markets where Amazon doesn't yet offer same-day delivery.\n\nIt also continues to change and in some instances upgrade its merchandise to appeal to a wider client base, including a more affluent customer. It recently launched a more upscale, health-branded product line, and it reaches this customer base through its website as well, since they're customers who might not come into its physical stores.\n\nWhy Walmart is winning\n\nWalmart's edge isn't only in its use of stores as delivery hubs, but in its size in general. There's a Walmart within 10 miles of 90% of the U.S. population, and that's just its U.S. business; it has more than 10,800 stores worldwide, giving it ample room to grow in many markets. And despite its size, it continues to identify white space in the U.S. for expansion.\n\nThe company got a major thumbs-up from investors last year for its resilience against tariffs. It has many levers to pull to cut costs, and it has leverage with suppliers. It's also an essentials business, and that simple fact means that customers always need its products. Since it's a discount retailer, it's more resilient when there's economic pressure.\n\nStory Continues\nTerms and Privacy Policy\nCA Privacy Notice\nYour Privacy Choices"
    },
    {
        "url": "https://finance.yahoo.com/news/walmart-wmt-earnings-expected-grow-150010001.html",
        "title": "Walmart (WMT) Earnings Expected to Grow: Should You Buy?",
        "detail": "Walmart (WMT) Earnings Expected to Grow: Should You Buy?\nZacks Equity Research\nThu, February 12, 2026 at 7:00 AM PST 4 min read\nIn this article:\nWMT\n\nThe market expects Walmart (WMT) to deliver a year-over-year increase in earnings on higher revenues when it reports results for the quarter ended January 2026. This widely-known consensus outlook is important in assessing the company's earnings picture, but a powerful factor that might influence its near-term stock price is how the actual results compare to these estimates.\n\nThe earnings report, which is expected to be released on February 19, might help the stock move higher if these key numbers are better than expectations. On the other hand, if they miss, the stock may move lower.\n\nWhile the sustainability of the immediate price change and future earnings expectations will mostly depend on management's discussion of business conditions on the earnings call, it's worth handicapping the probability of a positive EPS surprise.\n\nZacks Consensus Estimate\n\nThis world's largest retailer is expected to post quarterly earnings of $0.73 per share in its upcoming report, which represents a year-over-year change of +10.6%.\n\nRevenues are expected to be $189.99 billion, up 5.2% from the year-ago quarter.\n\nEstimate Revisions Trend\n\nThe consensus EPS estimate for the quarter has remained unchanged over the last 30 days. This is essentially a reflection of how the covering analysts have collectively reassessed their initial estimates over this period.\n\nInvestors should keep in mind that the direction of estimate revisions by each of the covering analysts may not always get reflected in the aggregate change.\n\nPrice, Consensus and EPS Surprise\n\nPrice, Consensus and EPS Surprise Chart for WMT\nEarnings Whisper\n\nEstimate revisions ahead of a company's earnings release offer clues to the business conditions for the period whose results are coming out. This insight is at the core of our proprietary surprise prediction model -- the Zacks Earnings ESP (Expected Surprise Prediction).\n\nThe Zacks Earnings ESP compares the Most Accurate Estimate to the Zacks Consensus Estimate for the quarter; the Most Accurate Estimate is a more recent version of the Zacks Consensus EPS estimate. The idea here is that analysts revising their estimates right before an earnings release have the latest information, which could potentially be more accurate than what they and others contributing to the consensus had predicted earlier.\n\nThus, a positive or negative Earnings ESP reading theoretically indicates the likely deviation of the actual earnings from the consensus estimate. However, the model's predictive power is significant for positive ESP readings only.\n\nA positive Earnings ESP is a strong predictor of an earnings beat, particularly when combined with a Zacks Rank #1 (Strong Buy), 2 (Buy) or 3 (Hold). Our research shows that stocks with this combination produce a positive surprise nearly 70% of the time, and a solid Zacks Rank actually increases the predictive power of Earnings ESP.\n\nStory Continues\nTerms and Privacy Policy\nCA Privacy Notice\nYour Privacy Choices"
    },
    {
        "url": "https://finance.yahoo.com/news/best-dividend-stock-buy-now-125000648.html",
        "title": "Best Dividend Stock to Buy Right Now: Walmart vs. Macy's",
        "detail": "Best Dividend Stock to Buy Right Now: Walmart vs. Macy's\nLawrence Rothman, CFA, The Motley Fool\nThu, February 12, 2026 at 4:50 AM PST 4 min read\nIn this article:\nWMT\nNVDA\nINTC\nM\n\nInvesting in dividend-paying stocks has its virtues. The payments can provide a regular source of income through various economic times. But you have to dig deeper to determine if the company can sustain its payouts. If they're tenuous, that could signal woes for the firm.\n\nTurning this analysis to individual stocks, two venerable retailers, Walmart (NASDAQ: WMT) and Macy's (NYSE: M), both pay dividends.\n\nWill AI create the world's first trillionaire?\u00a0Our team just released a report on the one little-known company, called an \"Indispensable Monopoly\" providing the critical technology Nvidia and Intel both need.\u00a0Continue \u00bb\n\nWhich one, if any, should dividend-seeking investors consider buying?\n\nImage source: Walmart.\nWalmart\n\nMost people know Walmart for its low-priced inventory of products and ubiquitous retail presence. Its Walmart and Sam's Club stores and multiple retail websites serve more than 270 million customers globally each week.\n\nIt's not just a popular shopping destination. Walmart also produces a healthy profit. Fiscal third-quarter operating profit, adjusted to remove foreign-currency translation effects, grew 8% year over year to $7.2 billion. The period ended on Oct. 31.\n\nIt produces enough profit to invest in the business and also pay a generous dividend. Walmart generated free cash flow (FCF), or operating cash flow less capital expenditures, of $8.8 billion for the prior nine months. That's well in excess of the $5.6 billion it pays out in dividends.\n\nCertainly, Walmart can afford its dividends. The board of directors also has a history of raising them, doing so annually for more than 50 straight years, making the company a Dividend King. That's certainly quite a feat.\n\nHowever, at the current dividend rate, the stock's 0.7% dividend yield is lower than the S&P 500's (SNPINDEX: ^GSPC) 1.1%. That's more a reflection of the stock's strong performance over the past year. Walmart stock trades up 169% (compared to the S&P 500's 70% gain) over the past three years.\n\nMacy's\n\nMany people know the Macy's brand, but the company has been dealing with challenges lately. Management implemented its turnaround plan, which includes revamping and closing some Macy's stores, changing the product assortment, and focusing on its luxury brands (Bloomingdale's and Bluemercury).\n\nThere's evidence that its plan has proven effective, albeit it's in the early days. The company's fiscal third-quarter same-store sales (comps) increased 3.4%. This figure measures owned-plus-licensed-plus marketplace sales. These include online sales and sales by departments licensed to others. The quarter ended on Nov. 1.\n\nStory Continues\nTerms and Privacy Policy\nCA Privacy Notice\nYour Privacy Choices"
    },
    {
        "url": "https://finance.yahoo.com/news/india-flipkart-explores-entry-food-114012946.html",
        "title": "India\u2019s Flipkart explores entry into food delivery segment",
        "detail": "India\u2019s Flipkart explores entry into food delivery segment\nUmesh Ellichipuram\nThu, February 12, 2026 at 3:40 AM PST 1 min read\nIn this article:\nWMT\nPAYTM.BO\n\nIndian e-commerce company Flipkart is considering a move into online food delivery and is preparing to test the service in Bengaluru, The Economic Times (ET) reported, citing people familiar with the matter.\n\nOwned by Walmart, Flipkart is aiming to start a pilot programme in the city around May\u2013June.\n\nA wider rollout could follow by the end of this year or early next year, depending on how the trials perform.\n\n\u201cFlipkart is evaluating the food delivery market while trying to identify a differentiated positioning in the space,\u201d one of the sources told the publication.\n\nAround two years ago, Flipkart had outlined plans to enter food delivery via the government-backed Open Network for Digital Commerce (ONDC), similar to ride-hailing services Ola and payment app Paytm.\n\nHowever, that initiative did not advance beyond the planning stage.\n\nA second person said Flipkart is examining two possible routes: launching its own standalone food delivery platform or introducing a buyer-side application on ONDC.\n\nBoth options are under active review, and the company has started putting together a team for the project.\n\nIf finalised, Flipkart\u2019s move would bring a new large competitor into a segment that has seen consolidation from more than a dozen operators to two major players, namely Zomato and Swiggy.\n\nUrban mobility startup Rapido trialled its Ownly food delivery service in Bengaluru around August 2025. It completed its city-wide rollout earlier this month.\n\n\"India\u2019s Flipkart explores entry into food delivery segment\" was originally created and published by Verdict Food Service, a GlobalData owned brand.\n\n\n\n\n\u00a0\n\n\nThe information on this site has been included in good faith for general informational purposes only. It is not intended to amount to advice on which you should rely, and we give no representation, warranty or guarantee, whether express or implied as to its accuracy or completeness. You must obtain professional or specialist advice before taking, or refraining from, any action on the basis of the content on our site.\n\nTerms and Privacy Policy\nCA Privacy Notice\nYour Privacy Choices"
    },
    {
        "url": "https://finance.yahoo.com/news/kroger-going-rough-period-ceo-111700866.html",
        "title": "Kroger is going through a rough period. Can its new CEO turn things around?",
        "detail": "Kroger is going through a rough period. Can its new CEO turn things around?\nSam Silverstein\nThu, February 12, 2026 at 3:17 AM PST 4 min read\nIn this article:\nKR\nWMT\n\nThis story was originally published on Grocery Dive. To receive daily news and insights, subscribe to our free daily Grocery Dive newsletter.\n\nWhen Walmart named Greg Foran president and CEO of its U.S. division in July 2014, the mega-retailer was bogged down by weak comparable-store sales growth and a disappointing profit outlook, while Kroger, one of its top competitors in the grocery space, was riding a multi-year wave of success.\n\nNearly a decade later, as he settles in as Kroger\u2019s new CEO, Foran again faces the task of rejuvenating a sprawling company going through a difficult period \u2014 with his now-roaring former employer as one of its chief obstacles.\n\nThat dynamic is a chief reason why Kroger\u2019s decision to bring on Foran as its new leader is a logical next step for the grocer as it looks to regain its footing as the nation\u2019s largest operator of conventional supermarkets, said Jason Schloetzer, an associate professor of business administration at Georgetown University\u2019s McDonough School of Business and an expert on CEO transitions.\n\n\u201cI think it gives him immediate legitimacy among stakeholders and also among employees \u2014 that this is somebody who appears to have done a good job previously at a chief rival,\u201d said Schloetzer. \u201cTo me, it just looks like a great, sensible hire by a board that went through a thoughtful process.\u201d\n\nForan, who spent nearly six years as CEO of Air New Zealand after he left Walmart in 2019, took over as chief executive of Kroger earlier this week. He replaced Ron Sargent, who became the grocery chain\u2019s interim CEO in March 2025 following the sudden resignation of former Chairman and CEO Rodney McMullen.\n\nRetail industry analysts said Foran\u2019s reputation as an expert in managing large-scale retail operations makes him well suited to tackle the challenge of turning Kroger in a new direction. Foran served as president and CEO of Walmart China and Walmart Asia before assuming the top post at Walmart U.S. Earlier in his career, he worked for Australian supermarket chain Woolworths.\n\n\u201cGreg has a rare combination of meticulous attention to detail in each store, surrounds himself with outstanding people, and somehow manages to coordinate everything across thousands of locations,\u201d said Thom Blischok, Chairman and CEO of The Dialogic Group, which provides growth advisory services to grocers and other retailers.\n\nThe fact that Kroger took nearly a year to identify a new CEO meant that the company had set a high bar for its next leader, said Arun Sundaram, senior vice president of CFRA Research\n\nStory Continues\nTerms and Privacy Policy\nCA Privacy Notice\nYour Privacy Choices"
    },
    {
        "url": "https://finance.yahoo.com/news/walmart-host-fourth-quarter-earnings-110000072.html",
        "title": "Walmart To Host Fourth Quarter Earnings Conference Call February 19, 2026",
        "detail": "This is a paid press release. Contact the press release distributor directly with any inquiries.\nWalmart To Host Fourth Quarter Earnings Conference Call February 19, 2026\nBusiness Wire\nThu, February 12, 2026 at 3:00 AM PST 1 min read\nIn this article:\nWMT\n\nBENTONVILLE, Ark., February 12, 2026--(BUSINESS WIRE)--Walmart Inc. (NASDAQ: WMT) announced it will release its fourth quarter earnings results at 6 a.m. CST and hold a live conference call with the investment community at 7 a.m. CST on Thursday, February 19, 2026. John Furner, president and chief executive officer, and John David Rainey, executive vice president and chief financial officer, will host the call to discuss the results and answer questions.\n\nLinks to access earnings information:\n\nEarnings Materials\n\nLive Webcast\n\nWebcast Archive\n\nAbout Walmart\n\nWalmart Inc. (NASDAQ: WMT) is a people-led, tech-powered omnichannel retailer helping people save money and live better - anytime and anywhere - in stores, online, and through their mobile devices. Each week, approximately 270 million customers and members visit more than 10,750 stores and numerous eCommerce websites in 19 countries. With fiscal year 2025 revenue of $681 billion, Walmart employs approximately 2.1 million associates worldwide. Walmart continues to be a leader in sustainability, corporate philanthropy, and employment opportunity. Additional information about Walmart can be found by visiting corporate.walmart.com, on Facebook at facebook.com/walmart, on X (formerly known as Twitter) at twitter.com/walmart, and on LinkedIn at linkedin.com/company/walmart.\n\nView source version on businesswire.com: https://www.businesswire.com/news/home/20260212080792/en/\n\nContacts\n\nInvestor Relations Contacts\nSteph Wissink\nSenior Vice President, Investor Relations\nir@walmart.com\n\nKary Brunner\nSr. Director, Investor Relations\n\nMedia Relations Contact\nJennifer Rodriguez\nVice President, Walmart Inc. Communications\nPress@walmart.com\n\nTerms and Privacy Policy\nCA Privacy Notice\nYour Privacy Choices"
    },
    {
        "url": "https://finance.yahoo.com/news/indian-textile-maker-welspuns-profit-095144910.html",
        "title": "Indian textile maker Welspun's profit nearly wiped out on US tariff-led slowdown",
        "detail": "Indian textile maker Welspun's profit nearly wiped out on US tariff-led slowdown\nReuters\nThu, February 12, 2026 at 1:51 AM PST 2 min read\nIn this article:\nWELCORP.BO\nWELSPUNLIV.BO\nWMT\nTSCO.L\n\nFeb 12 (Reuters) - Indian textile maker Welspun Living, which exports to global retailers including Walmart and Tesco, posted a slump in \u200cits quarterly profit on Thursday, as a U.S. tariff-triggered slowdown \u200cin exports squeezed its margins.\n\nWelspun's consolidated net profit came in at 2.1 million rupees ($23,178.81) for \u200bthe three-month period ended December 31, sharply down from 1.21 billion rupees in the year-ago period.\n\nResults included a one-time charge of 189.7 million rupees linked to India's new labour codes, implemented last November as part of the government's \u200cefforts to simplify regulations and \u2060encourage investment.\n\nRevenue from operations fell 9% to 22.62 billion rupees, while its earnings before interest, taxes, depreciation, and amortisation (EBITDA) \u2060margin narrowed by 493 basis points to 7.7%.\n\nKEY CONTEXT\n\nIndian textile exporters including Welspun and Trident reeled under the impact of steep U.S. tariffs for several \u200bmonths, with \u200bsome seeking new buyers in Europe \u200band offering discounts to U.S. \u200ccustomers to stay afloat.\n\nThese companies are now expecting better quarters as U.S. President Donald Trump announced a trade deal with India, slashing tariffs on Indian goods, just days after New Delhi struck a separate trade agreement with the European Union.\n\nWelspun Living, which supplies to many U.S. retailers including Costco \u200cWholesale and Target, derives more than 60% \u200bof its revenue from the United States \u200band roughly 18% from the \u200bUK and Europe.\n\nPEER COMPARISON\n\nValuation Estimates (next 12 Analysts' sentiment\n\n(next 12 months)\n\nmonths)\n\nRIC PE EV/EBI Revenue Profit Mean # of Stock to Div\n\nTDA growth (%) growth rating* analyst price yield\n\n(%) s target** (%)\n\nWelspun \u200cLiving WLSP.NS 22.29 10.91 16.12 157.62 Buy 9 0.92 1.21\n\nLtd\n\nArvind Ltd ARVN.BO 18.87 9.92 10.46 27.41 Strong 6 0.79 1.04\n\nBuy\n\nKPR Mill Ltd KPRM.NS 28.90 18.68 11.86 17.38 Buy 6 0.85 0.55\n\nVardhman VART.BO 14.91 9.47 6.99 12.59 Hold 5 1.09 1.04\n\nTextiles Ltd\n\n* Mean of \u200banalysts' ratings standardised \u200bto a scale of Strong Buy, Buy, Hold, Sell, and Strong Sell ** Ratio of the stock's last close to analysts' mean price \u200btarget; a ratio above \u200c1 means the stock is trading above the PT\n\nOCTOBER-DECEMBER STOCK PERFORMANCE\n\n-- \u200bAll data from LSEG\n\n-- $1 = 90.6000 Indian rupees\n\n(Reporting by Praveen Paramasivam \u200bin Chennai; Editing by Sherry Jacob-Phillips)\n\nTerms and Privacy Policy\nCA Privacy Notice\nYour Privacy Choices"
    },
    {
        "url": "https://finance.yahoo.com/news/3-trillion-dollar-stocks-soar-092600223.html",
        "title": "3 Trillion-Dollar Stocks That Can Soar Up to 90% in 2026, According to Select Wall Street Analysts",
        "detail": "3 Trillion-Dollar Stocks That Can Soar Up to 90% in 2026, According to Select Wall Street Analysts\nSean Williams, The Motley Fool\nThu, February 12, 2026 at 1:26 AM PST 7 min read\nIn this article:\n^GSPC\nWMT\nNVDA\nINTC\n\nWall Street's benchmark index, the S&P 500, is enjoying a historic run. Since 1928, it's gained at least 16% in three consecutive years on three separate occasions. Two of those three periods have occurred since 2019 (2019-2021 and 2023-2025).\n\nWhile game-changing technological trends, such as the rise of artificial intelligence (AI), have played a role in catapulting the broader market to new heights, it's Wall Street's trillion-dollar companies that have done a lot of the heavy lifting. Including Walmart, which became the newest member of the trillion-dollar club last week, 12 companies listed on U.S. exchanges have reached the elusive $1 trillion market cap.\n\nWill AI create the world's first trillionaire?\u00a0Our team just released a report on the one little-known company, called an \"Indispensable Monopoly\" providing the critical technology Nvidia and Intel both need.\u00a0Continue \u00bb\n\nImage source: Getty Images.\n\nAlthough it's unlikely that trillion-dollar stocks will deliver truly jaw-dropping investment returns going forward, these companies are, nonetheless, industry leaders that are fully capable of heading even higher -- and Wall Street analysts know it.\n\nWhile analysts are collectively bullish on all 12 trillion-dollar stocks listed in the U.S., there's outsize optimism for three of these companies. Based on the price targets of select Wall Street analysts, the following members of the trillion-dollar club can soar up to 90% in 2026.\n\nNvidia: Implied upside of 90%\n\nThe first trillion-dollar stock that's projected to skyrocket this year is the face of the AI revolution, Nvidia (NASDAQ: NVDA). As of February 2026, 63 Wall Street analysts have weighed in on Nvidia, with 59 rating it the equivalent of a strong buy or buy. One of these 59 analysts is Mark Lipacis of Evercore ISI, the institutional equities division of Evercore. Lipacis sees Nvidia's shares rising to $352, representing 90% upside from its Feb. 6 closing price.\n\nPretty much every analyst and everyday investor recognizes the data center dominance that Nvidia brings to the table. Its Hopper (H100), Blackwell, and Blackwell Ultra graphics processing units (GPUs) hold a near monopoly in AI-accelerated data centers.\n\nLipacis' outsize optimism is based on the belief that Nvidia will be the undisputed beneficiary of AI-driven parallel processing. In other words, customers will be able to leverage the compute superiority of Nvidia's GPUs and its CUDA software platform to run simultaneous tasks. With CEO Jensen Huang overseeing the rollout of an advanced GPU annually, it's unlikely that any external competitors will match or surpass the compute capabilities of Nvidia's AI hardware anytime soon.\n\nStory Continues\nTerms and Privacy Policy\nCA Privacy Notice\nYour Privacy Choices"
    },
    {
        "url": "https://finance.yahoo.com/news/est-e-lauder-sues-walmart-020143141.html",
        "title": "Est\u00e9e Lauder sues Walmart, claiming retail giant selling knockoffs",
        "detail": "Est\u00e9e Lauder sues Walmart, claiming retail giant selling knockoffs\nFernando Cervantes Jr., USA TODAY\nWed, February 11, 2026 at 6:01 PM PST 1 min read\nIn this article:\nEL\nWMT\n\nEst\u00e9e Lauder is suing Walmart in federal court alleging that the retailer sold counterfeit versions of the cosmetic company's fragrance and skin care products in its online store.\n\nThe lawsuit was filed on Monday, Feb. 9, in the California Central District Court. In it, Est\u00e9e Lauder accused Walmart of selling fake versions of its brands: Aveda, Clinique, La Mer, Le Labo and Tom Ford.\n\nEst\u00e9e Lauder said the products \"bear marks that are identical with, substantially indistinguishable from, or confusingly similar\u201d to products sold by the cosmetics company, according to court records posted by Reuters.\n\nAn Estee Lauder cosmetics counter is seen in Los Angeles, California, U.S., August 19, 2019.\n\nTo back up its claim, Est\u00e9e Lauder said in the lawsuit that it has bought and tested some of the alleged counterfeit products to test their authenticity and determined that they were not made by the company.\n\nMoreover, Est\u00e9e Lauder accused Walmart of being aware that it was selling counterfeit products on its website and that it did \u201cvery little\u201d to ensure products sold were authentic.\n\nIn an emailed statement to USA TODAY, Walmart said it had \"zero tolerance for counterfeit products.\"\n\n\"We will respond appropriately with the court when we are served,\" the retailer said.\n\nWhat products were allegedly sold?\n\nAccording to the lawsuit, the following counterfeit products were allegedly sold by Walmart on its website, Walmart.com:\n\nAveda hairbrushes\n\nClinique skin creams\n\nLa Mer lotion\n\nLa Mer moisturizers\n\nLe Labo fragrances\n\nTom Ford fragrances\n\nEst\u00e9e Lauder is asking Walmart to pay money for damages, as well as to stop any sales of the allegedly counterfeit products and any other products bearing the beauty company's trademark.\n\nFernando Cervantes Jr. is a trending news reporter for USA TODAY. Reach him at fernando.cervantes@usatodayco.com and follow him on X @fern_cerv_.\n\nThis article originally appeared on USA TODAY: Estee Lauder sues Walmart over alleged counterfeit products\n\nTerms and Privacy Policy\nCA Privacy Notice\nYour Privacy Choices"
    },
    {
        "url": "https://finance.yahoo.com/news/predicted-exxonmobil-join-1-trillion-012500780.html",
        "title": "I Predicted That ExxonMobil Would Join the $1 Trillion Club by 2030, But the Stock Is Already Up 24% in 2026. Is the High-Yield Dividend Stock Still a Buy Now?",
        "detail": "I Predicted That ExxonMobil Would Join the $1 Trillion Club by 2030, But the Stock Is Already Up 24% in 2026. Is the High-Yield Dividend Stock Still a Buy Now?\nDaniel Foelber, The Motley Fool\nWed, February 11, 2026 at 5:25 PM PST 4 min read\nIn this article:\nXOM\nWMT\nMETA\nAVGO\nTSLA\n\nThe $1 trillion club continues to get bigger, with Walmart becoming the 10th U.S. company to surpass $1 trillion in market capitalization. It joins Nvidia, Alphabet, Apple, Microsoft, Amazon, Meta Platforms, Broadcom, Tesla, and Berkshire Hathaway. Eli Lilly has been in and out of the club, and JPMorgan Chase needs less than a 15% gain to reach $1 trillion.\n\nI pegged ExxonMobil (NYSE: XOM), Visa, Oracle, and Netflix as dark horse candidates to reach $1 trillion by 2030. But ExxonMobil is off to the races so far this year -- up 23.9% year to date at the time of this writing, pushing its market cap to $622.9 billion.\n\nWhere to invest $1,000 right now? Our analyst team just revealed what they believe are the 10 best stocks to buy right now, when you join Stock Advisor.\u00a0See the stocks \u00bb\n\nHere's why ExxonMobil is soaring, and whether the high-yield dividend stock is still a buy now.\n\nImage source: Getty Images.\nA sectorwide rally\n\nEnergy has been the best-performing sector year to date, partly thanks to ExxonMobil, the sector's largest component.\n\n^IXE data by YCharts.\n\nAs you can see in the chart, other sectors that have done well are materials, consumer staples, and industrials. High-growth sectors like technology and communication services have lost value.\n\nAfter a multi-year, rip-roaring rally in artificial intelligence (AI) growth stocks, investors are taking a pause this year by questioning elevated valuations and outsized AI spending. The skepticism is somewhat warranted, especially when you have a company like Amazon saying it's going to spend $200 billion in 2026 capital expenditures, even though it only earned $139.5 billion in trailing 12-month cash from operations.\n\nExxonMobil is delivering results despite lower oil prices\n\nExxonMobil benefits from increased oil and gas demand from AI. But besides that, it is uniquely removed from the AI investment thesis. ExxonMobil has hard assets and a business model that is relatively insulated from AI. It stands out as a clear winner from AI, which can help improve operations and lower costs, rather than, say, a software company facing an existential threat.\n\nExxonMobil has a highly efficient production portfolio and expects to achieve 13% average earnings growth and double-digit cash flow growth per year through 2030. That guidance is based on mediocre oil prices -- not on hoping that oil prices rise and lift margins.\n\nExxonMobil's efficiency gains are largely thanks to its advanced assets, including its Permian Basin operations, liquefied natural gas, and offshore Guyana developments. These projects are particularly high-margin, and ExxonMobil expects them to account for 65% of its total 2030 oil-equivalent upstream volumes.\n\nStory Continues\nTerms and Privacy Policy\nCA Privacy Notice\nYour Privacy Choices"
    },
    {
        "url": "https://finance.yahoo.com/news/walmart-inc-wmt-price-target-004409912.html",
        "title": "Walmart Inc. (WMT) Price Target Increased at Oppenheimer as Firm Eyes Solid Q4",
        "detail": "Walmart Inc. (WMT) Price Target Increased at Oppenheimer as Firm Eyes Solid Q4\nVardah Gill\nWed, February 11, 2026 at 4:44 PM PST 3 min read\nIn this article:\nWMT\nOPY\n\nWalmart Inc. (NASDAQ:WMT) is included among the\n\n13 Best Roth IRA Stocks to Buy Now.\n\nWalmart Inc. (WMT) Price Target Increased at Oppenheimer as Firm Eyes Solid Q4\n\nOn February 9, Oppenheimer analyst Rupesh Parikh increased his price recommendation on Walmart Inc. (NASDAQ:WMT) to $140 from $125 and maintained an Outperform rating ahead of the company\u2019s quarterly results. The firm raised its Q4 EPS estimate toward the upper end of management\u2019s guidance, citing expectations for a strong holiday season, steady top-line momentum across the business, and possible support from favorable weather. Looking to fiscal 2026, Oppenheimer expects management to \"only\" guide in line with its long-term framework of 4% sales growth and 4% to 8% operating income growth. That outlook would fall short of the current Street expectation for 11.3% operating income growth. As a result, the firm believes it would be positioned to take advantage of any pullback in the stock rather than rely on a near-term upside catalyst. Walmart remains a top pick at Oppenheimer.\n\nOn February 3, Walmart became the first retailer to reach a $1 trillion market valuation. The milestone followed a year-long rally that pushed shares up nearly 26%, placing the company alongside large technology names such as Nvidia and Alphabet. The company\u2019s performance reflects its ability to appeal to a broad customer base. Walmart has attracted higher-income shoppers looking for value and convenience while continuing to serve its traditional lower-income customers. Over the past decade, the stock has gained 476%, compared with a 269.2% increase for the S&P 500. That outperformance has been tied in part to its ability to balance both segments of consumers.\n\nOver the last five years, Walmart expanded its online marketplace to more than half a billion items, introduced one-hour delivery, launched Walmart+ to compete with Amazon Prime, and built a $4 billion advertising business that has supported margins.\n\nThe company also invested heavily in artificial intelligence. It directed billions toward supply chain automation to improve fresh inventory management, speed up delivery times, and refine forecasting and search capabilities. Those efforts have contributed to 15 consecutive quarters of U.S. same-store sales outperformance, based on LSEG estimates. Investor confidence in Walmart\u2019s AI strategy has added momentum to the stock as more consumers shift grocery purchases online.\n\nWalmart Inc. (NASDAQ:WMT) operates as a technology-enabled omnichannel retailer. It runs retail and wholesale stores, clubs, e-commerce platforms, and mobile applications across the US, Africa, Canada, Central America, Chile, China, India, and Mexico. The company reports results through three segments: Walmart US, Walmart International, and Sam\u2019s Club US.\n\nStory Continues\nTerms and Privacy Policy\nCA Privacy Notice\nYour Privacy Choices"
    },
    {
        "url": "https://finance.yahoo.com/news/dot-takes-product-first-case-224239352.html",
        "title": "Make the Dot Takes Its Product-First Case to the Runway With Supima",
        "detail": "Make the Dot Takes Its Product-First Case to the Runway With Supima\nSourcing Journal \u00b7 Courtesy\nAlexandra Harrell\nWed, February 11, 2026 at 2:42 PM PST 5 min read\nIn this article:\nWMT\nTGT\nM\nKSS\n\nWelcome to the era digital craftsmanship: where the bottlenecks emerging designers face\u2014communicating product ideas, validating design decisions and securing buy-in before physical sampling\u2014mirror those faced by enterprise teams. At least, according to Make the Dot, a AI-native platform streamlining fashion product development for mass and mid-market retailers.\n\nTo address the industry\u2019s emerging digital-first demand, Make the Dot\u2019s platform brings design, development and merchandising into a single workflow\u2014all in attempt to bridge creative intent with commercial reality. By offering earlier visibility into how products are likely to look and perform, teams can visualize line architecture and product presentation before committing to physical mockups.\n\nMore from Sourcing Journal\n\nPhotoroom Develops 2026 GenAI Marketplace Blueprint\n\nReju Announces Site of First Commercial-Scale US Factory\n\nAI's Green Dilemma\n\nFounded in 2022 and operating between New York and Hong Kong, the platform has been used to develop products that are stocked at the likes of Walmart and Target as well as Macy\u2019s and Kohl\u2019s. Positioned as a collaborative digital workspace, Make the Dot claims it can deliver up to three times faster time-to-market and reduce physical sampling by as much as 60 percent.\n\nHow? Artificial intelligence, mostly.\n\nThose gains are driven by a suite of generative AI-enabled tools, including photorealistic rendering, digital fabric libraries and live collaboration features. The result, according to the Li & Fung partner, is a system that produces digital samples that are practical and producible\u2014and, notably, repeatable.\n\n\u201cFashion teams are under pressure to move faster, reduce waste and still deliver strong creative and financial results,\u201d said Theren Moodley, co-founder and chief growth officer. \u201cOur platform reflects how decisions are actually made\u2014connecting design intent, material choices and merchandising logic in one system.\u201d\n\nWhy? Because independent designers face the same structural challenge as large wholesale operations, according to co-founder and CEO, Emilie Ho: How to present ideas convincingly before physical production.\n\n\u201cA solo designer pitching boutiques with a suitcase of samples and a tailor flying across the country with fabric swatches for a single client meeting are navigating the same bottleneck that Make the Dot already solves for enterprise clients,\u201d Ho said. \u201cThe difference is scale, not workflow.\u201d\n\nThat question of scale is central to the company\u2019s next test: its inaugural fashion presentation on Feb. 24 in New York City. In partnership with Supima, \u201cRendered In Real Life\u201d will demonstrate just that\u2014if (and how) the same digital architecture used by independent labels can power global retail giants.\n\nStory Continues\nTerms and Privacy Policy\nCA Privacy Notice\nYour Privacy Choices"
    },
    {
        "url": "https://finance.yahoo.com/news/est-e-lauder-suit-tests-210933577.html",
        "title": "Est\u00e9e Lauder Suit Tests Walmart Marketplace Controls And Investor Sentiment",
        "detail": "Est\u00e9e Lauder Suit Tests Walmart Marketplace Controls And Investor Sentiment\nSimply Wall St\nWed, February 11, 2026 at 1:09 PM PST 4 min read\nIn this article:\nWMT\nEL\n\nFind winning stocks in any market cycle. Join 7 million investors using Simply Wall St's investing ideas for FREE.\n\nEst\u00e9e Lauder has sued Walmart, alleging that counterfeit versions of Aveda, Clinique, La Mer, Le Labo, and Tom Ford products were sold on Walmart's online marketplace.\n\nThe lawsuit claims Walmart allowed third party sellers to offer fake items and did not adequately ensure listings were limited to authorized, authentic products.\n\nThe case raises questions around Walmart's marketplace controls, its brand relationships, and potential legal and reputational risk linked to its e commerce operations.\n\nFor investors watching NasdaqGS:WMT, this legal dispute comes at a time when Walmart's shares trade around $126.7 and the stock has returned 23.5% over the past year. The longer term picture is positive in the article's data, with a very large 3 year return and a 176.4% return over 5 years, which reflects the role Walmart currently plays in US retail and online shopping.\n\nThe key issue now is how this lawsuit could influence Walmart's marketplace practices, brand partnerships, and customer trust. As the case progresses, investors may want to watch for any changes Walmart makes to third party seller oversight and how brands respond to its handling of authenticity concerns.\n\nStay updated on the most important news stories for Walmart by adding it to your watchlist or portfolio. Alternatively, explore our Community to discover new perspectives on Walmart.\n\nNasdaqGS:WMT 1-Year Stock Price Chart\n\nIs Walmart's balance sheet strong enough for future acquisitions? Dive into our detailed financial health analysis.\n\nThe Est\u00e9e Lauder lawsuit puts a spotlight on the controls around Walmart\u2019s third-party marketplace at the same time as the retailer leans more on e-commerce, advertising and higher-income shoppers for growth. For you as an investor, the near-term questions are less about direct financial hit and more about potential compliance costs, platform rule changes and any knock-on effects on brand relationships. If courts find Walmart liable or if a settlement includes tougher obligations, Walmart may need to invest further in verification, data tools and enforcement across its marketplace, which could add to operating expenses.\n\nHow This Fits Into The Walmart Narrative\n\nThe lawsuit directly links to the existing narrative around Walmart using AI-powered tools and digital platforms to run a large marketplace, and may accelerate investment in anti-counterfeit and compliance technology that supports long-term omni-channel ambitions.\n\nIt also highlights a pressure point in that same narrative, as tighter policing of third-party sellers could increase complexity and costs and potentially slow the pace at which Walmart can grow marketplace volume compared with Amazon or Target.\n\nThe current narrative focuses on growth drivers like AI, memberships and advertising, while this legal challenge underlines legal and reputational risk that may not be fully reflected in the story about operational efficiency and profit mix.\n\nStory Continues\nTerms and Privacy Policy\nCA Privacy Notice\nYour Privacy Choices"
    },
    {
        "url": "https://finance.yahoo.com/news/costco-becomes-launchpad-startups-testing-180713219.html",
        "title": "Costco Becomes a Launchpad for Startups Testing Consumer Products",
        "detail": "Costco Becomes a Launchpad for Startups Testing Consumer Products\nFaizan Farooque\nWed, February 11, 2026 at 10:07 AM PST 1 min read\nIn this article:\nCOST\nTGT\nWMT\n\nThis article first appeared on GuruFocus.\n\nCostco Wholesale Corporation (COST, Financials) has quietly become one of the most powerful launchpads for young consumer brands looking to break into national retail. Although the warehouse giant doesn't operate a formal accelerator program, its regional test launches are helping emerging players reach millions of shoppers and often, accelerate from local obscurity to national recognition in a matter of weeks.\n\nWarning! GuruFocus has detected 2 Warning Sign with MSFT.\n\nIs COST fairly valued? Test your thesis with our free DCF calculator.\n\nFor startups, the journey typically begins with a time-limited or regional test run. A positive result can lead to lightning-fast expansion, like beverage maker Hiyo, which went from a small Southern California trial to supplying 400 Costco warehouses across 47 states.\n\nUnlike traditional retailers such as Target (TGT) or Walmart (WMT), which work on longer annual reset cycles, Costco's short-term model lets brands test market fit without a long-term commitment. The warehouse format also pushes startups to rethink packaging, pallet design, and branding to stand out on Costco's minimalist sales floor.\n\nShares of Costco slipped 0.2% in premarket trading Tuesday but remain up 12.6% year to date, underscoring continued investor optimism around the retailer's agile merchandising strategy.\n\nTerms and Privacy Policy\nCA Privacy Notice\nYour Privacy Choices"
    },
    {
        "url": "https://finance.yahoo.com/news/angi-q4-earnings-call-highlights-175240332.html",
        "title": "Angi Q4 Earnings Call Highlights",
        "detail": "Angi Q4 Earnings Call Highlights\nMarketBeat\nWed, February 11, 2026 at 9:52 AM PST 8 min read\nIn this article:\nANGI\nWMT\nGOOG\nAngi logo\nKey Points\n\nMulti-year transformation: Management says Angi has \u201cgiven up about $500 million of lower quality revenue,\u201d doubled EBITDA, cut capex in half and moved to positive free cash flow while improving NPS, churn, customer success and repeat rates.\n\nConservative near-term outlook: Angi now expects \u201cvery modest negative growth\u201d in Q1 (guided down 1%\u20133%) and low-single-digit growth for the year, citing ongoing Google SEO and network-channel pressure and a deliberate shift to grow proprietary channels through increased brand and pro marketing.\n\nAI and LLM strategy to boost conversion: Angi is integrating LLMs (including a deal with Alexa) and has deployed on-site AI in the service-request path where users convert about 3.3\u00d7 better, positioning AI as a future \u201cagent\u201d to raise the share of hires going to Angi pros.\n\nInterested in Angi Inc.? Here are five stocks we like better.\n\nWalmart: Retail Juggernaut Has More Room to Grow for Investors\n\nAngi (NASDAQ:ANGI) executives highlighted what they described as a multi-year transformation toward higher-quality revenue, improved customer outcomes, and stronger cash generation, while laying out a more conservative near-term revenue outlook amid ongoing pressure from Google SEO and the company\u2019s network channel.\n\nManagement cites multi-year shift in mix and customer metrics\n\nCEO Jeff Kip said the company has \u201cgiven up about $500 million of lower quality revenue\u201d over the past three years, while \u201cdoubl[ing] our EBITDA\u201d and cutting capital expenditures in half, which he said swung Angi from negative to positive free cash flow.\n\n\u2192 Once Upon A Farm: Buy the $1B Growth Story?\n\nANGI Home Services Stock Providing Pullback Opportunities\n\nKip also pointed to operational and customer experience improvements, including:\n\nHomeowner Net Promoter Score (NPS) up \u201cmore than 30 points\u201d\n\nChurn down \u201cmore than 30%\u201d\n\nCustomer success rates up \u201cmore than 20%\u201d\n\nCustomer repeat rate turning positive in the fourth quarter by \u201cabout 10%\u201d\n\nHe added that Angi is seeing a \u201cmaterial stairstep improvement\u201d in year-over-year revenue changes, estimating \u201c700-900 basis points,\u201d and said January showed \u201cvery modest\u201d growth, though management does not \u201cfully expect growth\u201d in the first quarter.\n\nAI and LLM strategy: integrations, on-site conversion lift, and \u201cagent\u201d positioning\n\n\u2192 Verizon: Your Total Return Leader for 2026 Might Be Hiding in Plain Sight\n\nKip framed large language models (LLMs) as both a top-of-funnel opportunity and a channel diversification effort. He said Angi has started working with \u201cevery LLM,\u201d announced a deal with Amazon\u2019s Alexa, submitted an app to \u201canother major LLM,\u201d and is discussing \u201ctwo technical integrations\u201d based on the same underlying technology. However, he noted Angi does not yet have anything \u201clive\u201d and characterized current LLM-related traffic as modest and difficult to parse.\n\n\u7e7c\u7e8c\u95b1\u8b80\n\u689d\u6b3e \u53ca \u79c1\u96b1\u653f\u7b56\nCA Privacy Notice\nYour Privacy Choices"
    },
    {
        "url": "https://finance.yahoo.com/news/hasbro-ceo-chris-cocks-why-wizards-of-the-coast-and-digital-gaming-are-exploding-163715127.html",
        "title": "Hasbro CEO Chris Cocks: Why Wizards of the Coast and digital gaming are exploding",
        "detail": "Hasbro CEO Chris Cocks: Why Wizards of the Coast and digital gaming are exploding\nBrian Sozzi \u00b7 Executive Editor\nWed, February 11, 2026 at 8:37 AM PST 2 min read\nIn this article:\nWMT\nMAT\nHAS\nNFLX\n^IXIC\n\nHasbro (HAS) is entering a potentially holy grail year, led by whopping growth in its digital gaming business.\n\n\"I think whether it's Dungeons & Dragons or Magic: The Gathering or, you know, some of our licensed partners like Monopoly Go, it's really the community and bringing people together that really drives ... the power in gaming,\" Hasbro CEO Chris Cocks told me on Yahoo Finance's Opening Bid.\n\nAdded Cocks, \"I think [Magic: The Gathering] is what really separates it apart. The tens of millions of people who gather together and play around kitchen tables, and in 10,000 mom-and-pop hobby stores around the world. That's what people really crave, particularly in an increasingly digital world. Authentic people-to-people connection and shared passion.\"\n\nShares of the toymaker exploded 8% on Tuesday after the company easily beat fourth quarter profit estimates and offered upbeat guidance for 2026.\n\nThe Street gave Hasbro high marks for aggressive cost-cutting and strong sales momentum behind digital gaming platform Wizards of the Coast. Sales for the Wizards business surged 86% from the prior year, with operating margins up materially.\n\nThe company will also have a slew of new toys out this year tied to highly anticipated Disney movie releases like Toy Story 5.\n\nHasbro's outlook calls for another year of top-line growth and operating margin expansion.\n\n\"We continue to view Hasbro as the most compelling idea in our toy coverage, given the strength and durability of the Wizards/MTG engine, improving consumer products consistency, and a robust entertainment slate. The company enters 2026 with momentum, differentiated IP, expanding distribution, and strengthened financial flexibility, positioning Hasbro to outperform peers and deliver superior multi\u2011year earnings power, in our view,\" said Jefferies analyst Kylie Cohu.\n\nCohu lifted his price target by 24% on Hasbro to $120. That puts him toward the high end of Wall Street analyst price targets, according to Yahoo Finance data.\n\nCocks said the toy industry has bottomed out after a few challenging years.\n\n\"The toy category has been down, kind of like low-single-digit percentage [drop] per year for the last three years. We see that starting to flatten out and basically being flat for the next two to three years. We think Hasbro will benefit \u2014 we've got a great innovation portfolio coming out.\"\n\nBrian Sozzi is Yahoo Finance's Executive Editor and a member of Yahoo Finance's editorial leadership team. Follow Sozzi on X @BrianSozzi, Instagram, and LinkedIn. Tips on stories? Email brian.sozzi@yahoofinance.com.\n\nWeiterlesen\nAGB und Datenschutzerkl\u00e4rung\nCA Privacy Notice\nYour Privacy Choices"
    },
    {
        "url": "https://finance.yahoo.com/news/good-time-buy-walmart-stock-151300011.html",
        "title": "Is it a Good Time to Buy Walmart Stock at Its Current Price?",
        "detail": "Is it a Good Time to Buy Walmart Stock at Its Current Price?\nVrishali Bagree\nWed, February 11, 2026 at 7:13 AM PST 4 min read\nIn this article:\nWMT\nKR\nTGT\n^GSPC\n\nWalmart Inc. WMT continues to reinforce its standing as one of the most resilient and strategically positioned companies in global retail. The world\u2019s largest retailer has evolved far beyond its traditional big-box roots, combining everyday low prices with a powerful omnichannel ecosystem, expanding high-margin revenue streams and disciplined cost execution. Reflecting this strength and investor confidence in its transformation, Walmart recently crossed the $1 trillion market capitalization milestone.\n\nA Closer Look at WMT Stock\u2019s Momentum\n\nUnlike many consumer-facing companies grappling with demand volatility, Walmart continues to post steady traffic growth, supported by its value positioning and broad merchandise assortment. The company\u2019s shares have delivered strong gains over the past year and recently hit a 52-week high of $131.79 on Feb. 9.\u00a0\n\nOver the past year, Walmart shares have rallied 22.4%, outpacing the Zacks Retail \u2013 Wholesale sector\u2019s decline of 0.5% and the S&P 500\u2019s advance of 17.7%. The stock has also delivered stronger returns than key peers, with The Kroger Co. KR rising 3.4%, while Costco Wholesale Corporation COST and Target Corporation TGT declined 8.6% and 11.1%, respectively, over the same period.\n\nZacks Investment Research\n\n\nImage Source: Zacks Investment Research\n\nIs WMT\u2019s Premium Valuation Justified?\n\nAt present, Walmart trades at a forward price-to-earnings multiple of 42.93, slightly above the industry average of 39.81. The premium to Target and Kroger, which trade at 14.57 and 12.86, respectively, reflects Walmart\u2019s scale, diversified revenue streams and consistent earnings profile. While Costco commands a higher multiple of 46.21, WMT\u2019s valuation appears aligned with other large, high-quality retail operators. The stock\u2019s multiple suggests that investors continue to place value on its stable demand base and long-term growth initiatives.\n\nZacks Investment Research\n\n\nImage Source: Zacks Investment Research\n\nGrowth Engines Driving Walmart\u2019s Strength\n\nWalmart continues to gain market share across grocery, general merchandise and health & wellness categories. Its price leadership resonates particularly well in uncertain environments, attracting both middle and higher-income shoppers seeking value. Grocery remains a critical traffic engine, driving recurring visits and reinforcing customer loyalty. Transaction counts and unit volumes have remained positive, demonstrating that demand is not merely price-driven but supported by relevance and convenience.\n\nE-commerce is another powerful growth lever. Walmart\u2019s digital sales continue to expand at a healthy pace, fueled by store-fulfilled delivery, curbside pickup and marketplace growth. The company\u2019s integrated store network gives it a structural advantage, enabling faster delivery speeds and lower fulfillment costs relative to many competitors. Another major contributor is Walmart\u2019s growing exposure to high-margin revenue streams. Advertising, through Walmart Connect and its broader retail media initiatives, has emerged as a meaningful profit engine.\u00a0\n\nMembership income is also a stabilizing force. Sam\u2019s Club continues to see healthy renewal rates and membership growth, while Walmart+ is expanding its subscriber base. Membership programs enhance customer stickiness, increase basket sizes and create recurring revenue streams. As these businesses scale, they contribute meaningfully to operating income growth.\n\nInternational operations add another layer of strength. Markets such as Mexico and China continue to deliver solid performance, supported by digital adoption and format expansion. These regions provide long-term growth optionality and diversification beyond the U.S. consumer environment.\n\nOperational discipline plays a key role. Walmart\u2019s investments in automation, supply-chain modernization and data analytics are improving productivity and reducing costs. Strong inventory management has limited markdown risk while maintaining healthy in-stock levels. These efficiencies are allowing Walmart to pursue its long-standing goal of growing profits faster than sales.\n\nStory Continues\nTerms and Privacy Policy\nCA Privacy Notice\nYour Privacy Choices"
    },
    {
        "url": "https://finance.yahoo.com/news/cliganic-expands-national-retail-reach-150000856.html",
        "title": "Cliganic Expands National Retail Reach as Demand for Single-Ingredient, Multipurpose Beauty Grows",
        "detail": "This is a paid press release. Contact the press release distributor directly with any inquiries.\nCliganic Expands National Retail Reach as Demand for Single-Ingredient, Multipurpose Beauty Grows\nBusiness Wire\nWed, February 11, 2026 at 7:00 AM PST 2 min read\nIn this article:\nWMT\nGROV\nAMZN\nCastor oil, rosehip oil, jojoba oil, vitamin e oil, argan oil\n\nNEW YORK, February 11, 2026--(BUSINESS WIRE)--Cliganic\u00ae, the clean beauty and wellness brand known for its single-ingredient oils and everyday self-care essentials, today announced an expansion of its national retail presence across major U.S. markets, reflecting growing consumer demand for accessible, ingredient-first beauty solutions.\n\nAs part of this broader retail growth, Cliganic has recently expanded its availability at CVS Pharmacy\u00ae, rolling out to more than 800 locations nationwide, alongside existing placements at Erewhon, Walmart, Grove Collaborative, Macy\u2019s Online, Amazon, and additional retailers across the U.S.\n\nOver the past year, Cliganic has expanded its presence in national and specialty stores. The brand aims to make clean beauty more accessible by offering high-quality, multipurpose organic oils starting at $9.99, helping shoppers simplify their skincare and hair routines without adding extra steps or products.\n\nMeeting Shoppers Where They Are\n\nCliganic\u2019s clean beauty essentials are now available through a growing network of retailers, including:\n\nCVS Pharmacy\u00ae (800+ locations nationwide)\n\nErewhon\n\nWalmart (online and in-store)\n\nGrove Collaborative\n\nMacy\u2019s Online\n\nAmazon\n\nAdditional availability across Kroger, iHerb, Vitacost, Target.com, and more\n\nMulti-Use Essentials for Skin, Hair, and Body\n\nAcross select retail locations, Cliganic offers a curated lineup of its most-loved daily essentials, including:\n\nOrganic Jojoba Oil (4 oz)\n\nOrganic Castor Oil (4 oz)\n\nOrganic Argan Oil (4 oz)\n\nOrganic Rosehip Oil (1 oz)\n\nPure Non-GMO Vitamin E Oil (1 oz)\n\nEach product is USDA Certified Organic or Non-GMO (where applicable), cruelty-free, and made with ingredients people recognize according to the brand\u2019s clean beauty standards - with no fillers, no fragrances, and no unnecessary additives.\n\n\"With this continued retail expansion, we\u2019re making clean beauty part of everyday routines for more clean beauty shoppers than ever before,\" said Yoni Mousseiri, Co-Founder & CRO of Cliganic. \"Our goal is to build the modern beauty cabinet with products that are pure, effective, and offered at accessible price points - whether customers shop at Erewhon, Walmart, Grove Collaborative, Amazon, or other major retailers nationwide.\"\n\nAbout Cliganic\u00ae\n\nCliganic\u00ae is a clean beauty and wellness brand offering high-quality, single-ingredient essentials that are simple, affordable, and multipurpose. Best known for its USDA Organic oils and everyday self-care staples, Cliganic creates products made with ingredients people recognize and trust. Many products are certified organic, non-GMO, and cruelty-free, reflecting Cliganic\u2019s commitment to transparent quality and accessible clean beauty.\n\nStory Continues\nTerms and Privacy Policy\nCA Privacy Notice\nYour Privacy Choices"
    },
    {
        "url": "https://finance.yahoo.com/news/skyx-announces-launch-walmart-u-141900680.html",
        "title": "SKYX Announces Launch at Walmart, U.S. Leading Retailer, of its Ceiling Plug & Play SKYFAN & TURBO HEATER",
        "detail": "This is a paid press release. Contact the press release distributor directly with any inquiries.\nSKYX Announces Launch at Walmart, U.S. Leading Retailer, of its Ceiling Plug & Play SKYFAN & TURBO HEATER\nSKYX Platforms Corp.\nWed, February 11, 2026 at 6:19 AM PST 5 min read\nIn this article:\nSKYX\nWMT\nSKYX Platforms Corp.\n\nManagement Anticipates Significant Growth in Walmart Channel During 2026\n\nDriven by Strong Demand, SKYX Expects Additional Winter Launches in Leading U.S. Retailers and Big-Box Chains\n\nThe Company Anticipates that the Turbo Heater Launch Will Generate Significant Revenue in 2026 and Advance its Path to Cash-Flow Positive\n\nThe Ceiling Fan and Space Heater Categories Represent a Multi-Billion-Dollar Annual Market, with Tens of Millions of Units Sold Each Year in North America\n\nMIAMI, Feb. 11, 2026 (GLOBE NEWSWIRE) -- SKYX Platforms Corp. (NASDAQ: SKYX) (d/b/a SKYX Technologies) (the \u201cCompany\u201d or \u201cSKYX\u201d), a highly disruptive smart home platform technology company with over 100 pending and issued patents globally and 60 lighting and home d\u00e9cor websites, with a mission to make homes and buildings become safe and smart as the new standard, today announced it will launch its newly patented all-in-one ceiling plug & play SKYFAN & TURBO HEATER at U.S. leading retailer Walmart. Management anticipates significant growth in its Walmart business during 2026.\n\nThe innovative product\u2014combining a ceiling fan with a built-in turbo heater\u2014offers a safer, more efficient alternative to traditional space heaters and addresses a large year-round market opportunity across both winter and summer seasons. The combined ceiling fan and portable heater category is a multi-billion-dollar market, with tens of millions of units sold annually in North America.\n\nIn response to strong demand, SKYX intends to offer the product in six colors to serve both residential and commercial markets. Production is now underway with the Company\u2019s manufacturing partners, and SKYX expects to continue its broad rollout in Q1 2026 to align with the winter season.\n\nFor a Link to SKYFAN & Turbo Heater in Walmart: Click here\n\n\u00a0\n\nSKYFAN & TURBO HEATER\n\nSKYFAN & TURBO HEATER\n\nTo view a video of SKYX\u2019s turbo heater ceiling fan Click here\n\nLenny Sokolow, CEO of SKYX Platforms Corp., stated: \u201cWe are excited to begin launching our ceiling SKYFAN and Turbo Heater at a leading retailer such as Walmart, and we expect to continue expanding our presence across additional leading retailers and big-box chains. This product exemplifies our commitment to innovation, safety, and scalable global solutions. We believe this all-in-one offering will drive meaningful value for customers, partners, and shareholders.\u201d\n\nAbout SKYX Platforms Corp.\nSKYX Platforms Corp. (NASDAQ: SKYX) is a technology platform company focused on making homes and buildings safe, advanced, and smart as the new standard. As electricity is present in every home and building, SKYX is developing disruptive plug & play technologies designed to modernize traditional electrical infrastructure while improving safety, functionality, and ease of use.\n\nStory Continues\nTerms and Privacy Policy\nCA Privacy Notice\nYour Privacy Choices"
    },
    {
        "url": "https://finance.yahoo.com/news/does-ceo-time-tested-dividend-140002753.html",
        "title": "Does a New CEO Make This Time-Tested Dividend Stock a Buy Now?",
        "detail": "Does a New CEO Make This Time-Tested Dividend Stock a Buy Now?\nAanchal Sugandh\nWed, February 11, 2026 at 6:00 AM PST 4 min read\nIn this article:\nKR\nWMT\nANZFF\n\nFew leadership changes move markets instantly, but The Kroger Company\u2019s (KR) latest decision did exactly that. On Feb. 9, its\u00a0stock went up 3.9% as the company announced the appointment of former Walmart (WMT) executive\u00a0Greg Foran as chief executive, ending a year-long search after Rodney McMullen\u2019s ouster last March.\n\nForan brings a proven turnaround pedigree. He served as CEO of Air New Zealand Limited (ANZLY) for nearly five years until October 2025 and previously led Walmart\u2019s U.S. operations from 2014 to 2019. There, he rebuilt store performance and delivered 20 consecutive quarters of comparable sales growth.\n\nMore News from Barchart\n\n'If People in the Rest of the World Knew What I Know': MicroStrategy's Michael Saylor's Viral Message About MSTR Stock and Bitcoin to $10 Million\n\nMicrosoft is Bouncing Back from Its Post-Earnings Price Crash, But Watch This Before You Buy MSFT Stock\n\nMicroStrategy Is Now Down $4.5 Billion On Its $54 Billion Bitcoin Investment: What Does This Mean For Investors?\n\nGet exclusive insights with the FREE Barchart Brief newsletter. Subscribe now for quick, incisive midday market analysis you won't find anywhere else.\n\nCurrently, Kroger is navigating\u00a0pressured consumer spending and intensifying competition, including from Walmart itself. In that context, Foran\u2019s operational rigor and credibility could restore momentum and sharpen the company's execution.\n\nNow, with a battle-tested retailer at the helm, let us see whether Kroger can pair steadier execution with its long-standing dividend track record, and whether those income-backed shares truly earn a place in investors\u2019 carts.\n\nAbout Kroger Stock\n\nKroger is a Cincinnati, Ohio-based food and drug retailer managing more than 2,700 supermarkets, 2,200 pharmacies, and 1,700 fuel centers across 35 states and Washington, D.C. With a\u00a0nearly $44.4 billion market cap, it blends physical retail with digital platforms, manufacturing select foods while enabling omnichannel pickup and delivery.\n\nKR stock has\u00a0gained 4.2% over the past 52 weeks and jumped 5.56% during the last three months. Leadership developments further energized sentiment, driving an 6% jump in just the past five trading sessions.\n\nwww.barchart.com\n\nFrom a valuation standpoint, KR stock is trading at 14.61 times forward adjusted earnings and 0.30 times sales. Both metrics sit below industry averages, signaling a discounted profile.\n\nKroger\u2019s dividend record reinforces its defensive appeal. The company has raised its dividends for 19 consecutive years and pays $1.40 per share annually, translating into a 2% yield. Its latest $0.35 per share dividend is scheduled for March 1, payable to shareholders of record on Feb. 13.\n\nStory Continues\nTerms and Privacy Policy\nCA Privacy Notice\nYour Privacy Choices"
    }
]